{"mdsDat": {"x": [0.16711444465719993, 0.17436422837202634, 0.0910641683483397, -0.10119768114857425, -0.1418451842538151, -0.06932731648061483, 0.2597776668056994, -0.2013895138160579, -0.17856081248420408], "y": [0.117298002258138, -0.020783599171157057, -0.30749799678507367, 0.08194551987081207, -0.03785913112773708, -0.22466837983986704, 0.16741817820892235, 0.17946182133153826, 0.044685585254424044], "topics": [1, 2, 3, 4, 5, 6, 7, 8, 9], "cluster": [1, 1, 1, 1, 1, 1, 1, 1, 1], "Freq": [14.685873167051842, 13.937661493883912, 12.144897287482001, 11.418070731195957, 11.130586878016743, 10.707316899820237, 9.505743770057434, 9.305484434648125, 7.164365337843752]}, "tinfo": {"Term": ["ai", "information", "datum", "lecture", "assignment", "research", "ethical", "project", "topic", "science", "engineering", "link", "team", "presentation", "technology", "system", "study", "part", "final", "program", "philosophy", "apply", "design", "application", "discussion", "examination", "online", "detail", "issue", "assessment", "discretion", "sheet", "critique", "arrive", "ahead", "protocol", "mistake", "govern", "absent", "absence", "disrupt", "sharing", "miss", "inform", "disruption", "monitor", "cheating", "cheat", "quietly", "approximately", "pedagogical", "informal", "unsure", "hesitate", "slide", "cite", "attendance", "accord", "reflection", "wealth", "assignment", "presentation", "post", "late", "assign", "homework", "safety", "instructor", "call", "license", "appointment", "total", "expectation", "textbook", "reach", "classmate", "penalty", "emergency", "actively", "civil", "poster", "regularly", "assume", "comment", "disciplinary", "disability", "prepare", "announcement", "additional", "participation", "expect", "paper", "grade", "project", "share", "date", "exam", "submit", "section", "email", "material", "final", "write", "compute", "feedback", "require", "include", "discussion", "discuss", "make", "note", "policy", "reading", "ture", "intelligence", "brain", "educator", "mind", "attempt", "claim", "carefully", "essential", "consist", "suggest", "film", "connection", "argument", "scholar", "capitalism", "oxford_university", "easy", "belief", "freely", "engagement", "friend", "story", "hope", "picture", "lose", "love", "historical", "helpful", "put", "philosophy", "robot", "essay", "position", "long", "artificial", "live", "movie", "child", "respond", "moodle", "theme", "depth", "singularity", "express", "matter", "style", "podcast", "cognition", "hard", "spend", "strong", "philosophical", "word", "good", "question", "great", "teach", "discussion", "make", "talk", "issue", "book", "human", "find", "moral", "understand", "short", "show", "answer", "give", "machine", "ai", "reading", "write", "technical", "topic", "case", "time", "read", "acm", "fairness", "patent", "decision_making", "workplace", "status", "pdf", "predict", "edition", "hack", "careful", "rise", "poor", "police", "morality", "liability", "risk", "energy", "blame", "censorship", "american", "certification", "cost", "legislation", "criminal", "invisible", "informed", "inequality", "income", "improvement", "optional", "bias", "gender", "tech", "behavior", "transparency", "race", "discrimination", "accountability", "wire", "common", "chapter", "money", "black", "man", "lesson", "identity", "app", "economy", "ad", "election", "attack", "hide", "secure", "age", "surveillance", "responsibility", "draft", "software", "privacy", "user", "proposal", "wrong", "woman", "culture", "computer", "technology", "machine", "law", "public", "reading", "society", "social", "system", "people", "code", "design", "view", "turn", "ethical", "quality", "dismiss", "database", "highlight", "catalog", "component", "empirical", "assessment", "enrol", "inappropriate", "accident", "affect", "diverse", "working", "establish", "exceptional", "inclusive", "necessarily", "occur", "promote", "rate", "recognize", "reuse", "strive", "administrative", "trouble", "identify", "fact", "additionally", "respectful", "team", "objective", "situation", "community", "task", "rubric", "procedure", "piazza", "produce", "educational", "circumstance", "inclusion", "harassment", "voice", "excuse", "local", "org", "critically", "complaint", "fully", "return", "conduct", "practice", "major", "mail", "retrieve", "test", "relate", "evaluation", "activity", "hour", "regard", "professional", "code", "computer_science", "set", "case", "group", "review", "end", "issue", "report", "point", "policy", "schedule", "provide", "support", "understand", "develop", "follow", "ethical", "academic", "contact", "complete", "reinforcement", "mode", "autonomous", "charge", "dissertation", "employment", "fund", "fundamental", "funding", "governance", "honour", "investigate", "mailing", "panel", "institution", "partner", "postgraduate", "psychology", "regulatory", "senior", "intersection", "medicine", "neural", "freedom", "chain", "delivery", "administrator", "undergraduate", "title", "storage", "development", "language", "cookie", "fee", "home", "control", "game", "robotic", "career", "application", "machine_learne", "implementation", "master", "info", "minimum", "english", "feature", "cybersecurity", "artificial_intelligence", "option", "international", "key", "ai", "apply", "degree", "regulation", "management", "university", "theory", "module", "include", "agent", "area", "learn", "policy", "support", "knowledge", "system", "search", "study", "technology", "time", "skill", "develop", "service", "field", "term", "facility", "multi", "grant", "method", "reasoning", "industry", "enhance", "science", "capability", "publication", "innovation", "methodology", "model", "treatment", "month", "analytic", "invite", "industrial", "utility", "exact", "cultural", "annual", "complex", "figure", "statistical", "curriculum", "organize", "music", "edit", "leader", "datum", "engineering", "data", "intelligent", "algorithmic", "researcher", "consideration", "computational", "statistic", "centre", "influence", "research", "bachelor", "engineer", "proceeding", "design", "visit", "computing", "standard", "system", "social", "analysis", "project", "faculty", "ethical", "human", "decision", "part", "society", "current", "study", "people", "base", "academic", "problem", "introduction", "develop", "information", "core", "dilemma", "accompany", "lecturer", "play", "tutor", "unit", "ideally", "single", "quiz", "pattern", "refer", "verbal", "generate", "finish", "strongly", "intellectual", "primarily", "visual", "trust", "inquiry", "random", "anonymous", "building", "measure", "click", "loop", "link", "detect", "length", "lecture", "lab", "detail", "context", "critical", "break", "solve", "speak", "sort", "speaker", "coursework", "represent", "cryptography", "frame", "testing", "summary", "update", "version", "extension", "internet", "topic", "part", "add", "explain", "goal", "programming", "exercise", "day", "personal", "final", "level", "read", "page", "note", "web", "introduction", "minute", "analysis", "reading", "create", "time", "zoom", "remain", "strictly", "reserve", "registration", "register", "detection", "electronic", "warfare", "unique", "enroll", "introductory", "guarantee", "seek", "prior", "health", "sufficient", "card", "unable", "touch", "timely", "shopping", "shop", "sensitive", "device", "memory", "emphasize", "grow", "payment", "path", "basic", "campus", "employee", "pro", "profile", "obtain", "print", "applicable", "eligible", "assistance", "minimize", "documentation", "equal", "approval", "articulate", "check", "program", "transfer", "collect", "request", "gain", "online", "form", "credit", "number", "meet", "complete", "document", "website", "receive", "process", "session", "require", "information", "learning", "company", "provide", "site", "page", "learn", "professional", "meeting", "time", "date", "contact", "recommended_prerequisite", "substantial", "adapt", "actual", "professionalism", "classical", "utilitarianism", "ethical_theorie", "decide", "profession", "completion", "examiner", "intended_learning", "honor", "entire", "correct", "arise", "valid", "disabilitie", "construct", "examination", "vary", "prerequisite", "approve", "cycle", "offering", "group_webs", "co_operation", "avaialable", "disclose", "information_inserte", "autumn", "choose", "coordinator", "equipment", "programme_directory", "equivalent", "disposition", "discontinue", "literature", "examine", "main", "pass", "offer", "early", "information", "content", "study", "field", "search", "oral", "ethical", "web", "solution", "base", "problem", "describe", "apply", "format", "technology", "tool", "write", "computer", "aspect", "participation", "credit", "follow", "group"], "Freq": [396.0, 362.0, 251.0, 230.0, 277.0, 257.0, 350.0, 345.0, 222.0, 172.0, 173.0, 152.0, 165.0, 186.0, 358.0, 307.0, 228.0, 192.0, 229.0, 163.0, 161.0, 179.0, 187.0, 137.0, 284.0, 105.0, 151.0, 116.0, 274.0, 123.0, 5.527558253758172, 11.055116507516344, 5.527558253758172, 17.68818641202615, 7.73858155526144, 15.47716311052288, 11.055116507516344, 15.47716311052288, 7.73858155526144, 15.47716311052288, 7.73858155526144, 11.055116507516344, 51.95904758532681, 22.110233015032687, 5.527558253758172, 5.527558253758172, 7.73858155526144, 22.110233015032687, 5.527558253758172, 8.844093206013074, 5.527558253758172, 7.73858155526144, 5.527558253758172, 5.527558253758172, 70.7527456481046, 15.47716311052288, 76.28030390186277, 15.47716311052288, 69.64723399735296, 7.73858155526144, 277.4834243386602, 186.8314689770262, 106.12911847215689, 87.33542040937911, 86.22990875862747, 81.80786215562094, 39.79841942705884, 38.692907776307194, 35.3763728240523, 28.74330291954249, 28.74330291954249, 27.637791268790856, 27.637791268790856, 25.42676796728759, 24.32125631653595, 24.32125631653595, 24.32125631653595, 21.00472136428105, 19.89920971352942, 18.793698062777782, 17.68818641202615, 16.582674761274514, 16.582674761274514, 63.014164092843146, 16.582674761274514, 40.90393107781047, 42.0094427285621, 27.637791268790856, 63.014164092843146, 116.0787233289216, 71.85825729885623, 137.08344469320264, 98.39053691689544, 204.51965538905233, 46.43148933156864, 96.17951361539218, 57.48660583908498, 77.38581555261439, 80.7023505048693, 71.85825729885623, 119.3952582811765, 113.86770002741834, 117.18423497967323, 63.014164092843146, 65.22518739434643, 86.22990875862747, 98.39053691689544, 97.2850252661438, 67.4362106958497, 80.7023505048693, 71.85825729885623, 72.96376894960787, 69.64723399735296, 14.914243992715713, 60.80422550876406, 14.914243992715713, 14.914243992715713, 61.95147504666527, 14.914243992715713, 14.914243992715713, 14.914243992715713, 30.975737523332636, 14.914243992715713, 14.914243992715713, 29.828487985431426, 21.797741220122965, 55.06797781925802, 9.17799630320967, 6.883497227407252, 9.17799630320967, 17.20874306851813, 11.472495379012088, 6.883497227407252, 10.325245841110878, 8.03074676530846, 34.41748613703626, 5.736247689506044, 5.736247689506044, 19.50324214432055, 11.472495379012088, 12.619744916913296, 12.619744916913296, 41.30098336444351, 161.76218484407045, 131.93369685863902, 96.36896118370153, 63.098724584566476, 49.331730129751975, 47.03723105394956, 41.30098336444351, 39.0064842886411, 25.239489833826593, 24.092240295925382, 22.944990758024176, 21.797741220122965, 21.797741220122965, 20.650491682221755, 20.650491682221755, 20.650491682221755, 19.50324214432055, 18.35599260641934, 18.35599260641934, 17.20874306851813, 17.20874306851813, 17.20874306851813, 79.1602181151834, 88.33821441839306, 115.8722033280221, 173.2346802230825, 26.3867393717278, 94.07446210789912, 149.14243992715714, 143.40619223765108, 40.1537338265423, 133.0809463965402, 52.7734787434556, 102.10520887320757, 72.27672088777615, 74.57121996357857, 69.98222181197373, 59.65697597086285, 52.7734787434556, 51.626229205554395, 72.27672088777615, 68.83497227407253, 102.10520887320757, 92.9272125699979, 79.1602181151834, 58.50972643296164, 65.39322366036889, 57.36247689506043, 58.50972643296164, 56.21522735715922, 50.01568008510656, 50.01568008510656, 13.33751468936175, 12.226055131914938, 10.003136017021314, 15.560433804255377, 7.780216902127688, 10.003136017021314, 13.33751468936175, 20.006272034042627, 6.668757344680875, 20.006272034042627, 7.780216902127688, 11.114595574468126, 15.560433804255377, 12.226055131914938, 66.68757344680876, 10.003136017021314, 12.226055131914938, 13.33751468936175, 6.668757344680875, 5.557297787234063, 17.783352919149003, 16.67189336170219, 13.33751468936175, 13.33751468936175, 7.780216902127688, 12.226055131914938, 12.226055131914938, 6.668757344680875, 84.47092636595775, 71.13341167659601, 57.79589698723426, 43.34692274042569, 40.012544068085255, 38.90108451063844, 38.90108451063844, 36.67816539574481, 36.67816539574481, 36.67816539574481, 28.89794849361713, 90.02822415319181, 25.563569821276687, 24.452110263829876, 24.452110263829876, 21.117731591489438, 21.117731591489438, 21.117731591489438, 21.117731591489438, 20.006272034042627, 18.894812476595813, 17.783352919149003, 17.783352919149003, 17.783352919149003, 52.23859920000019, 43.34692274042569, 65.57611388936195, 27.78648893617031, 106.700117514894, 143.3782829106388, 57.79589698723426, 28.89794849361713, 28.89794849361713, 45.56984185531931, 28.89794849361713, 128.92930866383026, 161.16163582978783, 85.58238592340456, 60.018816102127886, 47.792760970212946, 118.92617264680895, 60.018816102127886, 84.47092636595775, 91.13968371063862, 55.57297787234062, 56.68443742978744, 58.90735654468107, 43.34692274042569, 42.235463182978876, 44.458382297872504, 20.5159317764169, 6.838643925472299, 18.236383801259464, 12.537513863365882, 6.838643925472299, 27.354575701889196, 5.6988699378935825, 123.09559065850138, 12.537513863365882, 10.25796588820845, 5.6988699378935825, 19.37615778883818, 21.655705763995613, 13.677287850944598, 11.397739875787165, 9.118191900629732, 15.956835826102031, 9.118191900629732, 12.537513863365882, 13.677287850944598, 7.9784179130510156, 20.5159317764169, 6.838643925472299, 5.6988699378935825, 11.397739875787165, 12.537513863365882, 47.870507478306095, 29.63412367704663, 7.9784179130510156, 6.838643925472299, 165.2672281989139, 71.80576121745914, 51.289829441042244, 49.01028146588481, 47.870507478306095, 44.45118551556995, 28.494349689467914, 23.935253739153048, 22.79547975157433, 22.79547975157433, 22.79547975157433, 19.37615778883818, 18.236383801259464, 17.096609813680747, 17.096609813680747, 17.096609813680747, 15.956835826102031, 15.956835826102031, 14.817061838523315, 14.817061838523315, 34.19321962736149, 68.38643925472299, 85.48304906840374, 43.311411527991226, 25.075027726731765, 55.84892539135711, 63.827343304408124, 78.64440514293145, 47.870507478306095, 88.9023710311399, 77.50463115535273, 35.332993614940214, 94.60124096903347, 91.18191900629732, 44.45118551556995, 45.59095950314866, 83.2035010932463, 107.13875483239936, 52.42960342862096, 58.12847336651454, 105.99898084482064, 61.54779532925069, 61.54779532925069, 92.32169299387604, 64.96711729198684, 66.10689127956556, 53.56937741619968, 55.84892539135711, 55.84892539135711, 59.26824735409326, 63.827343304408124, 53.56937741619968, 51.289829441042244, 52.42960342862096, 8.817708004697572, 11.022135005871965, 39.67968602113907, 15.43098900822075, 6.613281003523178, 12.124348506459162, 27.55533751467991, 29.759764515854304, 19.839843010569535, 34.16861851820309, 7.715494504110375, 9.919921505284767, 5.511067502935982, 13.226562007046356, 18.737629509982337, 17.635416009395144, 15.43098900822075, 13.226562007046356, 17.635416009395144, 15.43098900822075, 6.613281003523178, 13.226562007046356, 8.817708004697572, 11.022135005871965, 8.817708004697572, 13.226562007046356, 6.613281003523178, 52.90624802818542, 15.43098900822075, 8.817708004697572, 83.76822604462693, 71.64387753816777, 52.90624802818542, 49.599607526423846, 39.67968602113907, 34.16861851820309, 29.759764515854304, 27.55533751467991, 26.45312401409271, 135.57226057222516, 23.146483512331127, 20.942056511156732, 19.839843010569535, 19.839843010569535, 18.737629509982337, 17.635416009395144, 16.533202508807946, 15.43098900822075, 69.43945053699338, 37.475259019964675, 33.06640501761589, 54.00846152877262, 294.2910046567814, 111.32356355930683, 50.70182102701103, 30.8619780164415, 42.98632652290066, 50.70182102701103, 51.804034527598226, 37.475259019964675, 99.19921505284769, 41.884113022313464, 40.78189952172627, 83.76822604462693, 87.07486654638852, 51.804034527598226, 45.19075352407505, 78.25715854169094, 50.70182102701103, 66.13281003523178, 71.64387753816777, 65.03059653464459, 44.08854002348786, 46.29296702466225, 41.884113022313464, 41.884113022313464, 40.78189952172627, 10.984796954071777, 5.492398477035889, 23.06807360355073, 95.56773350042445, 24.166553298957908, 32.95439086221533, 20.871114212736373, 172.46131217892687, 21.969593908143555, 21.969593908143555, 23.06807360355073, 16.477195431107663, 64.81030202902348, 5.492398477035889, 10.984796954071777, 23.06807360355073, 12.083276649478954, 21.969593908143555, 5.492398477035889, 5.492398477035889, 18.67415482192202, 16.477195431107663, 20.871114212736373, 10.984796954071777, 21.969593908143555, 23.06807360355073, 12.083276649478954, 10.984796954071777, 32.95439086221533, 12.083276649478954, 251.55185024824368, 172.46131217892687, 86.77989593716703, 57.12094416117324, 29.658951775993796, 28.56047208058662, 27.46199238517944, 24.166553298957908, 19.772634517329198, 19.772634517329198, 15.378715735700487, 249.3548908574293, 28.56047208058662, 71.40118020146654, 35.15135025302968, 128.52212436263977, 53.82550507495171, 38.44678933925122, 31.85591116680815, 138.40844162130438, 104.35557106368186, 65.90878172443065, 114.24188832234648, 41.742228425472746, 105.45405075908904, 79.09053806931679, 40.64374873006557, 61.51486294280195, 47.23462690250863, 39.545269034658396, 52.72702537954452, 40.64374873006557, 42.840708120879924, 39.545269034658396, 39.545269034658396, 37.34830964384404, 36.24982994843686, 36.24982994843686, 30.33603717834069, 12.359126257842503, 7.864898527717957, 25.841809448216143, 13.482683190373638, 11.235569325311367, 50.56006196390115, 5.6177846626556835, 24.718252515685005, 83.14321300730411, 6.741341595186819, 10.11201239278023, 7.864898527717957, 10.11201239278023, 11.235569325311367, 13.482683190373638, 14.606240122904778, 10.11201239278023, 12.359126257842503, 26.965366380747277, 13.482683190373638, 8.988455460249092, 7.864898527717957, 15.729797055435913, 20.22402478556046, 49.43650503137001, 17.976910920498185, 152.80374282423458, 10.11201239278023, 21.347581718091597, 230.329171168883, 101.1201239278023, 115.72636405070708, 41.571606503652056, 41.571606503652056, 25.841809448216143, 24.718252515685005, 23.594695583153868, 22.471138650622734, 19.100467853029322, 17.976910920498185, 16.85335398796705, 16.85335398796705, 15.729797055435913, 13.482683190373638, 38.200935706058644, 51.683618896432286, 35.95382184099637, 23.594695583153868, 71.90764368199274, 157.29797055435913, 131.45616110614299, 35.95382184099637, 60.67207435668138, 73.03120061452388, 58.42496049161911, 35.95382184099637, 97.74945313020889, 56.17784662655683, 111.23213632058253, 57.301403559087966, 89.88455460249094, 74.15475754705501, 76.40187141211729, 58.42496049161911, 66.28985901933706, 39.32449263858978, 52.807175828963416, 70.78408674946161, 43.81872036871433, 52.807175828963416, 20.33740278399275, 13.558268522661836, 7.908989971552737, 13.558268522661836, 44.064372698650956, 37.28523843732005, 14.688124232883654, 38.41509414754187, 12.428412812440016, 11.298557102218195, 9.038845681774557, 7.908989971552737, 12.428412812440016, 19.207547073770936, 45.19422840887278, 18.077691363549114, 12.428412812440016, 9.038845681774557, 7.908989971552737, 12.428412812440016, 9.038845681774557, 9.038845681774557, 9.038845681774557, 10.168701391996375, 23.726969914658213, 10.168701391996375, 6.779134261330918, 10.168701391996375, 42.934516988429145, 7.908989971552737, 73.44062116441827, 65.53163119286553, 27.11653704532367, 21.467258494214573, 19.207547073770936, 18.077691363549114, 16.947835653327292, 16.947835653327292, 15.817979943105474, 15.817979943105474, 14.688124232883654, 14.688124232883654, 13.558268522661836, 13.558268522661836, 12.428412812440016, 56.492785511090986, 141.23196377772746, 24.85682562488003, 23.726969914658213, 57.6226412213128, 20.33740278399275, 112.98557102218197, 77.96004400530555, 83.60932255641465, 53.10321838042552, 44.064372698650956, 84.73917826663646, 48.583795539538244, 54.23307409064734, 66.66148690308735, 56.492785511090986, 50.84350695998188, 92.6481682381892, 142.36181948794925, 51.9733626702037, 33.895671306654584, 81.349611135971, 39.54494985776368, 63.271919772421896, 80.2197554257492, 62.14206406220007, 39.54494985776368, 59.88235264175644, 45.19422840887278, 41.80466127820733, 5.560114849942836, 6.672137819931403, 13.344275639862806, 10.008206729897104, 11.120229699885671, 5.560114849942836, 6.672137819931403, 7.784160789919971, 20.016413459794208, 7.784160789919971, 25.576528309737046, 38.92080394959985, 12.232252669874239, 10.008206729897104, 20.016413459794208, 17.792367519817077, 15.568321579839942, 6.672137819931403, 15.568321579839942, 12.232252669874239, 105.64218214891389, 8.896183759908538, 31.136643159679885, 23.35248236975991, 25.576528309737046, 15.568321579839942, 7.784160789919971, 7.784160789919971, 7.784160789919971, 7.784160789919971, 46.70496473951982, 27.800574249714177, 84.51374571913111, 17.792367519817077, 13.344275639862806, 12.232252669874239, 10.008206729897104, 8.896183759908538, 7.784160789919971, 48.929010679496955, 33.360689099657016, 38.92080394959985, 30.024620189691312, 73.39351601924542, 26.688551279725612, 179.0356981681593, 76.72958492921114, 110.09027402886815, 56.71317146941693, 61.1612633493712, 22.240459399771343, 134.55477936861664, 57.82519443940549, 36.69675800962271, 62.27328631935977, 65.60935522932546, 32.24866612966845, 67.8334011693026, 28.912597219702747, 76.72958492921114, 32.24866612966845, 44.480918799542685, 42.256872859565554, 31.136643159679885, 36.69675800962271, 33.360689099657016, 34.47271206964558, 34.47271206964558], "Total": [396.0, 362.0, 251.0, 230.0, 277.0, 257.0, 350.0, 345.0, 222.0, 172.0, 173.0, 152.0, 165.0, 186.0, 358.0, 307.0, 228.0, 192.0, 229.0, 163.0, 161.0, 179.0, 187.0, 137.0, 284.0, 105.0, 151.0, 116.0, 274.0, 123.0, 5.527558253758172, 11.055116507516344, 5.527558253758172, 17.68818641202615, 7.73858155526144, 15.47716311052288, 11.055116507516344, 15.47716311052288, 7.73858155526144, 15.47716311052288, 7.73858155526144, 11.055116507516344, 51.95904758532681, 22.110233015032687, 5.527558253758172, 5.527558253758172, 7.73858155526144, 22.110233015032687, 5.527558253758172, 8.844093206013074, 5.527558253758172, 7.73858155526144, 5.527558253758172, 5.527558253758172, 70.7527456481046, 15.47716311052288, 76.28030390186277, 15.47716311052288, 69.64723399735296, 7.73858155526144, 277.4834243386602, 186.8314689770262, 106.12911847215689, 87.33542040937911, 86.22990875862747, 81.80786215562094, 39.79841942705884, 38.692907776307194, 35.3763728240523, 28.74330291954249, 28.74330291954249, 27.637791268790856, 27.637791268790856, 25.42676796728759, 24.32125631653595, 24.32125631653595, 24.32125631653595, 21.00472136428105, 19.89920971352942, 18.793698062777782, 17.68818641202615, 16.582674761274514, 16.582674761274514, 64.13772102537428, 16.582674761274514, 43.151044942872744, 45.38011352615551, 28.777565256369574, 72.0530097746177, 153.9227308764455, 89.05952481705187, 205.207638806173, 138.80398460038865, 345.43657309012235, 55.35895577159754, 141.37374202426497, 73.08267843651507, 112.4113425694908, 120.07723336498455, 102.36436147484537, 208.5269286452792, 229.68883449960572, 240.82537189439932, 94.0571525291161, 106.21816688897901, 189.9926725712848, 248.9244347127203, 284.60332366223565, 135.81323758705787, 273.52785554788034, 173.83665702071056, 280.44925180315084, 352.28470596362143, 14.914243992715713, 60.80422550876406, 14.914243992715713, 14.914243992715713, 61.95147504666527, 14.914243992715713, 14.914243992715713, 14.914243992715713, 30.975737523332636, 14.914243992715713, 14.914243992715713, 29.828487985431426, 21.797741220122965, 55.06797781925802, 9.17799630320967, 6.883497227407252, 9.17799630320967, 17.20874306851813, 11.472495379012088, 6.883497227407252, 10.325245841110878, 8.03074676530846, 34.41748613703626, 5.736247689506044, 5.736247689506044, 19.50324214432055, 11.472495379012088, 12.619744916913296, 12.619744916913296, 41.30098336444351, 161.76218484407045, 131.93369685863902, 96.36896118370153, 63.098724584566476, 49.331730129751975, 47.03723105394956, 41.30098336444351, 39.0064842886411, 25.239489833826593, 24.092240295925382, 22.944990758024176, 21.797741220122965, 21.797741220122965, 20.650491682221755, 20.650491682221755, 20.650491682221755, 19.50324214432055, 18.35599260641934, 18.35599260641934, 17.20874306851813, 17.20874306851813, 17.20874306851813, 84.72033296512623, 102.81550309533354, 140.08891110122792, 263.24485681468934, 28.591166372902194, 146.9135016428442, 284.60332366223565, 273.52785554788034, 50.21929216458197, 274.94998612472705, 74.88371175848829, 210.0936954361415, 127.6424421215716, 137.93906346413252, 125.83114720333084, 100.78097959639491, 83.6354567598971, 84.32214298703659, 167.49188933119913, 154.41735819747709, 396.396213529989, 352.28470596362143, 240.82537189439932, 113.69955706626797, 222.691194214728, 159.24013281022877, 281.5558291191431, 192.5312712912188, 50.01568008510656, 50.01568008510656, 13.33751468936175, 12.226055131914938, 10.003136017021314, 15.560433804255377, 7.780216902127688, 10.003136017021314, 13.33751468936175, 20.006272034042627, 6.668757344680875, 20.006272034042627, 7.780216902127688, 11.114595574468126, 15.560433804255377, 12.226055131914938, 66.68757344680876, 10.003136017021314, 12.226055131914938, 13.33751468936175, 6.668757344680875, 5.557297787234063, 17.783352919149003, 16.67189336170219, 13.33751468936175, 13.33751468936175, 7.780216902127688, 12.226055131914938, 12.226055131914938, 6.668757344680875, 84.47092636595775, 71.13341167659601, 57.79589698723426, 43.34692274042569, 40.012544068085255, 38.90108451063844, 38.90108451063844, 36.67816539574481, 36.67816539574481, 36.67816539574481, 28.89794849361713, 91.15178108572294, 25.563569821276687, 24.452110263829876, 24.452110263829876, 21.117731591489438, 21.117731591489438, 21.117731591489438, 21.117731591489438, 20.006272034042627, 18.894812476595813, 17.783352919149003, 17.783352919149003, 17.783352919149003, 53.344110850751825, 44.4941722783269, 73.3146954446234, 28.89851190615888, 139.85843508209857, 203.01605873737915, 70.97765333212038, 31.102375494791524, 31.145062358679404, 56.96758173110648, 32.232528727651534, 244.1068510511026, 358.17761093023864, 154.41735819747709, 94.18743462033098, 68.80119695062763, 352.28470596362143, 114.9689375087469, 223.01971705700112, 307.8052838736339, 109.98372105722069, 151.17299693784634, 187.42948090732085, 73.17541072585712, 63.89116894697449, 350.5416695950486, 20.5159317764169, 6.838643925472299, 18.236383801259464, 12.537513863365882, 6.838643925472299, 27.354575701889196, 5.6988699378935825, 123.09559065850138, 12.537513863365882, 10.25796588820845, 5.6988699378935825, 19.37615778883818, 21.655705763995613, 13.677287850944598, 11.397739875787165, 9.118191900629732, 15.956835826102031, 9.118191900629732, 12.537513863365882, 13.677287850944598, 7.9784179130510156, 20.5159317764169, 6.838643925472299, 5.6988699378935825, 11.397739875787165, 12.537513863365882, 47.870507478306095, 29.63412367704663, 7.9784179130510156, 6.838643925472299, 165.2672281989139, 71.80576121745914, 51.289829441042244, 49.01028146588481, 47.870507478306095, 44.45118551556995, 28.494349689467914, 23.935253739153048, 22.79547975157433, 22.79547975157433, 22.79547975157433, 19.37615778883818, 18.236383801259464, 17.096609813680747, 17.096609813680747, 17.096609813680747, 15.956835826102031, 15.956835826102031, 14.817061838523315, 14.817061838523315, 35.32307533758331, 72.79529325707178, 96.59764464287187, 46.64579020033166, 26.18648728417858, 63.633086181277086, 82.56497281439046, 107.5570023626342, 60.03113563657407, 129.80630210895038, 113.4584529963491, 42.005131434871615, 157.84178472664073, 151.17299693784634, 61.13153006539845, 63.567870423646845, 159.24013281022877, 237.33411981162357, 82.49419993800991, 99.42945673095805, 274.94998612472705, 115.7866281134038, 122.03184802535199, 280.44925180315084, 152.115291900141, 189.2771407497897, 105.3734119437979, 125.83114720333084, 138.39172236445623, 190.6751388827068, 350.5416695950486, 121.20054454430428, 93.09449071924956, 148.2890113951431, 8.817708004697572, 11.022135005871965, 39.67968602113907, 15.43098900822075, 6.613281003523178, 12.124348506459162, 27.55533751467991, 29.759764515854304, 19.839843010569535, 34.16861851820309, 7.715494504110375, 9.919921505284767, 5.511067502935982, 13.226562007046356, 18.737629509982337, 17.635416009395144, 15.43098900822075, 13.226562007046356, 17.635416009395144, 15.43098900822075, 6.613281003523178, 13.226562007046356, 8.817708004697572, 11.022135005871965, 8.817708004697572, 13.226562007046356, 6.613281003523178, 52.90624802818542, 15.43098900822075, 8.817708004697572, 83.76822604462693, 71.64387753816777, 52.90624802818542, 49.599607526423846, 39.67968602113907, 34.16861851820309, 29.759764515854304, 27.55533751467991, 26.45312401409271, 137.8518085473826, 23.146483512331127, 20.942056511156732, 19.839843010569535, 19.839843010569535, 18.737629509982337, 17.635416009395144, 16.533202508807946, 15.43098900822075, 70.54496218774501, 38.57373871537185, 34.19626072783771, 59.62624619142831, 396.396213529989, 179.15696472860944, 66.26879285159937, 36.415581547147404, 59.663854010020394, 76.9166227413215, 79.60460877731241, 50.65701536485081, 248.9244347127203, 68.27085239404127, 65.24640486147474, 253.53819090804828, 280.44925180315084, 105.3734119437979, 84.63609253751875, 307.8052838736339, 111.86308437638223, 228.95010944364446, 358.17761093023864, 281.5558291191431, 91.95904750179395, 138.39172236445623, 87.28662525568109, 98.59728449173039, 96.46863010123297, 10.984796954071777, 5.492398477035889, 23.06807360355073, 95.56773350042445, 24.166553298957908, 32.95439086221533, 20.871114212736373, 172.46131217892687, 21.969593908143555, 21.969593908143555, 23.06807360355073, 16.477195431107663, 64.81030202902348, 5.492398477035889, 10.984796954071777, 23.06807360355073, 12.083276649478954, 21.969593908143555, 5.492398477035889, 5.492398477035889, 18.67415482192202, 16.477195431107663, 20.871114212736373, 10.984796954071777, 21.969593908143555, 23.06807360355073, 12.083276649478954, 10.984796954071777, 32.95439086221533, 12.083276649478954, 251.55185024824368, 173.5911678891487, 86.77989593716703, 57.12094416117324, 29.658951775993796, 28.56047208058662, 27.46199238517944, 24.166553298957908, 19.772634517329198, 19.772634517329198, 15.378715735700487, 257.15058560989183, 29.684029013117758, 82.78900179989681, 38.48572892537012, 187.42948090732085, 66.1157068392186, 45.188130934438036, 37.55478110470173, 307.8052838736339, 223.01971705700112, 136.50832507321115, 345.43657309012235, 64.30813749757576, 350.5416695950486, 210.0936954361415, 67.31877810878908, 192.97102404894494, 114.9689375087469, 79.54673057387454, 228.95010944364446, 109.98372105722069, 143.69146696079156, 121.20054454430428, 161.407611764958, 147.23365110342704, 138.39172236445623, 362.06279790722306, 30.33603717834069, 12.359126257842503, 7.864898527717957, 25.841809448216143, 13.482683190373638, 11.235569325311367, 50.56006196390115, 5.6177846626556835, 24.718252515685005, 83.14321300730411, 6.741341595186819, 10.11201239278023, 7.864898527717957, 10.11201239278023, 11.235569325311367, 13.482683190373638, 14.606240122904778, 10.11201239278023, 12.359126257842503, 26.965366380747277, 13.482683190373638, 8.988455460249092, 7.864898527717957, 15.729797055435913, 20.22402478556046, 49.43650503137001, 17.976910920498185, 152.80374282423458, 10.11201239278023, 21.347581718091597, 230.329171168883, 101.1201239278023, 116.82857755129427, 41.571606503652056, 41.571606503652056, 25.841809448216143, 24.718252515685005, 23.594695583153868, 22.471138650622734, 19.100467853029322, 17.976910920498185, 16.85335398796705, 16.85335398796705, 15.729797055435913, 13.482683190373638, 39.30314920664584, 53.96316687158972, 37.09359582857508, 24.706718553142437, 89.68504869444656, 222.691194214728, 192.97102404894494, 41.60310039210547, 78.53267055264658, 99.24600232883436, 79.29607470435548, 42.732956102327286, 161.86912887380367, 81.92108736695683, 229.68883449960572, 92.57223557787825, 192.5312712912188, 158.74937087239073, 173.83665702071056, 116.25015493102461, 147.23365110342704, 55.99638600029197, 136.50832507321115, 352.28470596362143, 97.62642008469624, 281.5558291191431, 20.33740278399275, 13.558268522661836, 7.908989971552737, 13.558268522661836, 44.064372698650956, 37.28523843732005, 14.688124232883654, 38.41509414754187, 12.428412812440016, 11.298557102218195, 9.038845681774557, 7.908989971552737, 12.428412812440016, 19.207547073770936, 45.19422840887278, 18.077691363549114, 12.428412812440016, 9.038845681774557, 7.908989971552737, 12.428412812440016, 9.038845681774557, 9.038845681774557, 9.038845681774557, 10.168701391996375, 23.726969914658213, 10.168701391996375, 6.779134261330918, 10.168701391996375, 42.934516988429145, 7.908989971552737, 73.44062116441827, 65.53163119286553, 27.11653704532367, 21.467258494214573, 19.207547073770936, 18.077691363549114, 16.947835653327292, 16.947835653327292, 15.817979943105474, 15.817979943105474, 14.688124232883654, 14.688124232883654, 13.558268522661836, 13.558268522661836, 12.428412812440016, 60.9256438788386, 163.20155768587102, 25.968848594868597, 24.838429472105027, 67.6308479512099, 21.439616284579948, 151.56304354273385, 106.11177032650264, 116.97001165607168, 79.318020094736, 62.32421025183612, 148.2890113951431, 71.79954020532256, 84.26036425206664, 115.35609009005474, 91.64413576412068, 79.4039790405685, 189.9926725712848, 362.06279790722306, 83.9375541872324, 45.01026688112271, 189.2771407497897, 60.673386287546464, 158.74937087239073, 253.53819090804828, 157.84178472664073, 71.45862150996774, 281.5558291191431, 141.37374202426497, 93.09449071924956, 5.560114849942836, 6.672137819931403, 13.344275639862806, 10.008206729897104, 11.120229699885671, 5.560114849942836, 6.672137819931403, 7.784160789919971, 20.016413459794208, 7.784160789919971, 25.576528309737046, 38.92080394959985, 12.232252669874239, 10.008206729897104, 20.016413459794208, 17.792367519817077, 15.568321579839942, 6.672137819931403, 15.568321579839942, 12.232252669874239, 105.64218214891389, 8.896183759908538, 31.136643159679885, 23.35248236975991, 25.576528309737046, 15.568321579839942, 7.784160789919971, 7.784160789919971, 7.784160789919971, 7.784160789919971, 46.70496473951982, 27.800574249714177, 85.65351970670983, 17.792367519817077, 13.344275639862806, 12.232252669874239, 10.008206729897104, 8.896183759908538, 7.784160789919971, 50.03122418008415, 34.459168795064194, 41.11776334041421, 33.395290987284724, 102.76976448501273, 33.46768554105653, 362.06279790722306, 132.4382542295009, 228.95010944364446, 98.59728449173039, 111.86308437638223, 27.768017653529515, 350.5416695950486, 116.25015493102461, 61.14886827345259, 143.69146696079156, 161.407611764958, 50.485049930927914, 179.15696472860944, 43.72965905822606, 358.17761093023864, 72.45624311597845, 240.82537189439932, 244.1068510511026, 66.94790762623832, 153.9227308764455, 116.97001165607168, 190.6751388827068, 237.33411981162357], "Category": ["Default", "Default", "Default", "Default", "Default", "Default", "Default", "Default", "Default", "Default", "Default", "Default", "Default", "Default", "Default", "Default", "Default", "Default", "Default", "Default", "Default", "Default", "Default", "Default", "Default", "Default", "Default", "Default", "Default", "Default", "Topic1", "Topic1", "Topic1", "Topic1", "Topic1", "Topic1", "Topic1", "Topic1", "Topic1", "Topic1", "Topic1", "Topic1", "Topic1", "Topic1", "Topic1", "Topic1", "Topic1", "Topic1", "Topic1", "Topic1", "Topic1", "Topic1", "Topic1", "Topic1", "Topic1", "Topic1", "Topic1", "Topic1", "Topic1", "Topic1", "Topic1", "Topic1", "Topic1", "Topic1", "Topic1", "Topic1", "Topic1", "Topic1", "Topic1", "Topic1", "Topic1", "Topic1", "Topic1", "Topic1", "Topic1", "Topic1", "Topic1", "Topic1", "Topic1", "Topic1", "Topic1", "Topic1", "Topic1", "Topic1", "Topic1", "Topic1", "Topic1", "Topic1", "Topic1", "Topic1", "Topic1", "Topic1", "Topic1", "Topic1", "Topic1", "Topic1", "Topic1", "Topic1", "Topic1", "Topic1", "Topic1", "Topic1", "Topic1", "Topic1", "Topic1", "Topic1", "Topic1", "Topic1", "Topic1", "Topic1", "Topic1", "Topic1", "Topic1", "Topic2", "Topic2", "Topic2", "Topic2", "Topic2", "Topic2", "Topic2", "Topic2", "Topic2", "Topic2", "Topic2", "Topic2", "Topic2", "Topic2", "Topic2", "Topic2", "Topic2", "Topic2", "Topic2", "Topic2", "Topic2", "Topic2", "Topic2", "Topic2", "Topic2", "Topic2", "Topic2", "Topic2", "Topic2", "Topic2", "Topic2", "Topic2", "Topic2", "Topic2", "Topic2", "Topic2", "Topic2", "Topic2", "Topic2", "Topic2", "Topic2", "Topic2", "Topic2", "Topic2", "Topic2", "Topic2", "Topic2", "Topic2", "Topic2", "Topic2", "Topic2", "Topic2", "Topic2", "Topic2", "Topic2", "Topic2", "Topic2", "Topic2", "Topic2", "Topic2", "Topic2", "Topic2", "Topic2", "Topic2", "Topic2", "Topic2", "Topic2", "Topic2", "Topic2", "Topic2", "Topic2", "Topic2", "Topic2", "Topic2", "Topic2", "Topic2", "Topic2", "Topic2", "Topic2", "Topic2", "Topic3", "Topic3", "Topic3", "Topic3", "Topic3", "Topic3", "Topic3", "Topic3", "Topic3", "Topic3", "Topic3", "Topic3", "Topic3", "Topic3", "Topic3", "Topic3", "Topic3", "Topic3", "Topic3", "Topic3", "Topic3", "Topic3", "Topic3", "Topic3", "Topic3", "Topic3", "Topic3", "Topic3", "Topic3", "Topic3", "Topic3", "Topic3", "Topic3", "Topic3", "Topic3", "Topic3", "Topic3", "Topic3", "Topic3", "Topic3", "Topic3", "Topic3", "Topic3", "Topic3", "Topic3", "Topic3", "Topic3", "Topic3", "Topic3", "Topic3", "Topic3", "Topic3", "Topic3", "Topic3", "Topic3", "Topic3", "Topic3", "Topic3", "Topic3", "Topic3", "Topic3", "Topic3", "Topic3", "Topic3", "Topic3", "Topic3", "Topic3", "Topic3", "Topic3", "Topic3", "Topic3", "Topic3", "Topic3", "Topic3", "Topic3", "Topic3", "Topic3", "Topic3", "Topic3", "Topic3", "Topic4", "Topic4", "Topic4", "Topic4", "Topic4", "Topic4", "Topic4", "Topic4", "Topic4", "Topic4", "Topic4", "Topic4", "Topic4", "Topic4", "Topic4", "Topic4", "Topic4", "Topic4", "Topic4", "Topic4", "Topic4", "Topic4", "Topic4", "Topic4", "Topic4", "Topic4", "Topic4", "Topic4", "Topic4", "Topic4", "Topic4", "Topic4", "Topic4", "Topic4", "Topic4", "Topic4", "Topic4", "Topic4", "Topic4", "Topic4", "Topic4", "Topic4", "Topic4", "Topic4", "Topic4", "Topic4", "Topic4", "Topic4", "Topic4", "Topic4", "Topic4", "Topic4", "Topic4", "Topic4", "Topic4", "Topic4", "Topic4", "Topic4", "Topic4", "Topic4", "Topic4", "Topic4", "Topic4", "Topic4", "Topic4", "Topic4", "Topic4", "Topic4", "Topic4", "Topic4", "Topic4", "Topic4", "Topic4", "Topic4", "Topic4", "Topic4", "Topic4", "Topic4", "Topic4", "Topic4", "Topic4", "Topic4", "Topic4", "Topic4", "Topic5", "Topic5", "Topic5", "Topic5", "Topic5", "Topic5", "Topic5", "Topic5", "Topic5", "Topic5", "Topic5", "Topic5", "Topic5", "Topic5", "Topic5", "Topic5", "Topic5", "Topic5", "Topic5", "Topic5", "Topic5", "Topic5", "Topic5", "Topic5", "Topic5", "Topic5", "Topic5", "Topic5", "Topic5", "Topic5", "Topic5", "Topic5", "Topic5", "Topic5", "Topic5", "Topic5", "Topic5", "Topic5", "Topic5", "Topic5", "Topic5", "Topic5", "Topic5", "Topic5", "Topic5", "Topic5", "Topic5", "Topic5", "Topic5", "Topic5", "Topic5", "Topic5", "Topic5", "Topic5", "Topic5", "Topic5", "Topic5", "Topic5", "Topic5", "Topic5", "Topic5", "Topic5", "Topic5", "Topic5", "Topic5", "Topic5", "Topic5", "Topic5", "Topic5", "Topic5", "Topic5", "Topic5", "Topic5", "Topic5", "Topic5", "Topic5", "Topic5", "Topic6", "Topic6", "Topic6", "Topic6", "Topic6", "Topic6", "Topic6", "Topic6", "Topic6", "Topic6", "Topic6", "Topic6", "Topic6", "Topic6", "Topic6", "Topic6", "Topic6", "Topic6", "Topic6", "Topic6", "Topic6", "Topic6", "Topic6", "Topic6", "Topic6", "Topic6", "Topic6", "Topic6", "Topic6", "Topic6", "Topic6", "Topic6", "Topic6", "Topic6", "Topic6", "Topic6", "Topic6", "Topic6", "Topic6", "Topic6", "Topic6", "Topic6", "Topic6", "Topic6", "Topic6", "Topic6", "Topic6", "Topic6", "Topic6", "Topic6", "Topic6", "Topic6", "Topic6", "Topic6", "Topic6", "Topic6", "Topic6", "Topic6", "Topic6", "Topic6", "Topic6", "Topic6", "Topic6", "Topic6", "Topic6", "Topic6", "Topic6", "Topic6", "Topic7", "Topic7", "Topic7", "Topic7", "Topic7", "Topic7", "Topic7", "Topic7", "Topic7", "Topic7", "Topic7", "Topic7", "Topic7", "Topic7", "Topic7", "Topic7", "Topic7", "Topic7", "Topic7", "Topic7", "Topic7", "Topic7", "Topic7", "Topic7", "Topic7", "Topic7", "Topic7", "Topic7", "Topic7", "Topic7", "Topic7", "Topic7", "Topic7", "Topic7", "Topic7", "Topic7", "Topic7", "Topic7", "Topic7", "Topic7", "Topic7", "Topic7", "Topic7", "Topic7", "Topic7", "Topic7", "Topic7", "Topic7", "Topic7", "Topic7", "Topic7", "Topic7", "Topic7", "Topic7", "Topic7", "Topic7", "Topic7", "Topic7", "Topic7", "Topic7", "Topic7", "Topic7", "Topic7", "Topic7", "Topic7", "Topic7", "Topic7", "Topic7", "Topic7", "Topic7", "Topic7", "Topic8", "Topic8", "Topic8", "Topic8", "Topic8", "Topic8", "Topic8", "Topic8", "Topic8", "Topic8", "Topic8", "Topic8", "Topic8", "Topic8", "Topic8", "Topic8", "Topic8", "Topic8", "Topic8", "Topic8", "Topic8", "Topic8", "Topic8", "Topic8", "Topic8", "Topic8", "Topic8", "Topic8", "Topic8", "Topic8", "Topic8", "Topic8", "Topic8", "Topic8", "Topic8", "Topic8", "Topic8", "Topic8", "Topic8", "Topic8", "Topic8", "Topic8", "Topic8", "Topic8", "Topic8", "Topic8", "Topic8", "Topic8", "Topic8", "Topic8", "Topic8", "Topic8", "Topic8", "Topic8", "Topic8", "Topic8", "Topic8", "Topic8", "Topic8", "Topic8", "Topic8", "Topic8", "Topic8", "Topic8", "Topic8", "Topic8", "Topic8", "Topic8", "Topic8", "Topic8", "Topic8", "Topic8", "Topic8", "Topic8", "Topic8", "Topic9", "Topic9", "Topic9", "Topic9", "Topic9", "Topic9", "Topic9", "Topic9", "Topic9", "Topic9", "Topic9", "Topic9", "Topic9", "Topic9", "Topic9", "Topic9", "Topic9", "Topic9", "Topic9", "Topic9", "Topic9", "Topic9", "Topic9", "Topic9", "Topic9", "Topic9", "Topic9", "Topic9", "Topic9", "Topic9", "Topic9", "Topic9", "Topic9", "Topic9", "Topic9", "Topic9", "Topic9", "Topic9", "Topic9", "Topic9", "Topic9", "Topic9", "Topic9", "Topic9", "Topic9", "Topic9", "Topic9", "Topic9", "Topic9", "Topic9", "Topic9", "Topic9", "Topic9", "Topic9", "Topic9", "Topic9", "Topic9", "Topic9", "Topic9", "Topic9", "Topic9", "Topic9", "Topic9", "Topic9", "Topic9", "Topic9", "Topic9", "Topic9"], "logprob": [30.0, 29.0, 28.0, 27.0, 26.0, 25.0, 24.0, 23.0, 22.0, 21.0, 20.0, 19.0, 18.0, 17.0, 16.0, 15.0, 14.0, 13.0, 12.0, 11.0, 10.0, 9.0, 8.0, 7.0, 6.0, 5.0, 4.0, 3.0, 2.0, 1.0, -7.2336, -6.5405, -7.2336, -6.0704, -6.8971, -6.204, -6.5405, -6.204, -6.8971, -6.204, -6.8971, -6.5405, -4.9929, -5.8473, -7.2336, -7.2336, -6.8971, -5.8473, -7.2336, -6.7636, -7.2336, -6.8971, -7.2336, -7.2336, -4.6842, -6.204, -4.6089, -6.204, -4.6999, -6.8971, -3.3176, -3.7131, -4.2787, -4.4736, -4.4863, -4.539, -5.2595, -5.2877, -5.3773, -5.5849, -5.5849, -5.6242, -5.6242, -5.7075, -5.752, -5.752, -5.752, -5.8986, -5.9527, -6.0098, -6.0704, -6.135, -6.135, -4.8, -6.135, -5.2321, -5.2055, -5.6242, -4.8, -4.1891, -4.6687, -4.0228, -4.3544, -3.6227, -5.1054, -4.3771, -4.8918, -4.5945, -4.5526, -4.6687, -4.1609, -4.2083, -4.1796, -4.8, -4.7655, -4.4863, -4.3544, -4.3657, -4.7322, -4.5526, -4.6687, -4.6534, -4.6999, -6.1887, -4.7834, -6.1887, -6.1887, -4.7647, -6.1887, -6.1887, -6.1887, -5.4579, -6.1887, -6.1887, -5.4956, -5.8092, -4.8825, -6.6742, -6.9619, -6.6742, -6.0456, -6.4511, -6.9619, -6.5565, -6.8078, -5.3525, -7.1442, -7.1442, -5.9205, -6.4511, -6.3558, -6.3558, -5.1702, -3.8049, -4.0088, -4.3229, -4.7464, -4.9925, -5.0401, -5.1702, -5.2273, -5.6626, -5.7092, -5.758, -5.8092, -5.8092, -5.8633, -5.8633, -5.8633, -5.9205, -5.9811, -5.9811, -6.0456, -6.0456, -6.0456, -4.5196, -4.4099, -4.1386, -3.7364, -5.6182, -4.347, -3.8862, -3.9254, -5.1983, -4.0001, -4.925, -4.2651, -4.6106, -4.5793, -4.6428, -4.8024, -4.925, -4.947, -4.6106, -4.6593, -4.2651, -4.3592, -4.5196, -4.8219, -4.7106, -4.8417, -4.8219, -4.8619, -4.841, -4.841, -6.1628, -6.2498, -6.4505, -6.0086, -6.7018, -6.4505, -6.1628, -5.7573, -6.8559, -5.7573, -6.7018, -6.3451, -6.0086, -6.2498, -4.5534, -6.4505, -6.2498, -6.1628, -6.8559, -7.0383, -5.8751, -5.9396, -6.1628, -6.1628, -6.7018, -6.2498, -6.2498, -6.8559, -4.317, -4.4888, -4.6965, -4.9841, -5.0642, -5.0923, -5.0923, -5.1512, -5.1512, -5.1512, -5.3896, -4.2532, -5.5122, -5.5567, -5.5567, -5.7033, -5.7033, -5.7033, -5.7033, -5.7573, -5.8145, -5.8751, -5.8751, -5.8751, -4.7975, -4.9841, -4.5702, -5.4288, -4.0833, -3.7879, -4.6965, -5.3896, -5.3896, -4.9341, -5.3896, -3.8941, -3.671, -4.3039, -4.6587, -4.8865, -3.9749, -4.6587, -4.317, -4.241, -4.7357, -4.7159, -4.6774, -4.9841, -5.0101, -4.9588, -5.6705, -6.7691, -5.7882, -6.1629, -6.7691, -5.3828, -6.9514, -3.8787, -6.1629, -6.3636, -6.9514, -5.7276, -5.6164, -6.0759, -6.2582, -6.4814, -5.9218, -6.4814, -6.1629, -6.0759, -6.6149, -5.6705, -6.7691, -6.9514, -6.2582, -6.1629, -4.8232, -5.3027, -6.6149, -6.7691, -3.5841, -4.4177, -4.7542, -4.7996, -4.8232, -4.8973, -5.342, -5.5163, -5.5651, -5.5651, -5.5651, -5.7276, -5.7882, -5.8528, -5.8528, -5.8528, -5.9218, -5.9218, -5.9959, -5.9959, -5.1596, -4.4665, -4.2433, -4.9232, -5.4698, -4.669, -4.5355, -4.3267, -4.8232, -4.2041, -4.3413, -5.1268, -4.142, -4.1788, -4.8973, -4.8719, -4.2704, -4.0175, -4.7322, -4.629, -4.0282, -4.5718, -4.5718, -4.1664, -4.5178, -4.5004, -4.7107, -4.669, -4.669, -4.6096, -4.5355, -4.7107, -4.7542, -4.7322, -6.4894, -6.2663, -4.9853, -5.9298, -6.7771, -6.1709, -5.35, -5.273, -5.6785, -5.1348, -6.6229, -6.3716, -6.9594, -6.0839, -5.7356, -5.7962, -5.9298, -6.0839, -5.7962, -5.9298, -6.7771, -6.0839, -6.4894, -6.2663, -6.4894, -6.0839, -6.7771, -4.6976, -5.9298, -6.4894, -4.2381, -4.3944, -4.6976, -4.7622, -4.9853, -5.1348, -5.273, -5.35, -5.3908, -3.7567, -5.5243, -5.6244, -5.6785, -5.6785, -5.7356, -5.7962, -5.8608, -5.9298, -4.4257, -5.0425, -5.1676, -4.677, -2.9816, -3.9537, -4.7402, -5.2366, -4.9053, -4.7402, -4.7187, -5.0425, -4.069, -4.9313, -4.9579, -4.2381, -4.1994, -4.7187, -4.8553, -4.3062, -4.7402, -4.4745, -4.3944, -4.4913, -4.88, -4.8312, -4.9313, -4.9313, -4.9579, -6.2309, -6.924, -5.4889, -4.0676, -5.4424, -5.1323, -5.589, -3.4772, -5.5377, -5.5377, -5.4889, -5.8254, -4.4559, -6.924, -6.2309, -5.4889, -6.1356, -5.5377, -6.924, -6.924, -5.7002, -5.8254, -5.589, -6.2309, -5.5377, -5.4889, -6.1356, -6.2309, -5.1323, -6.1356, -3.0997, -3.4772, -4.164, -4.5822, -5.2376, -5.2754, -5.3146, -5.4424, -5.6431, -5.6431, -5.8944, -3.1085, -5.2754, -4.3591, -5.0677, -3.7713, -4.6416, -4.9781, -5.1662, -3.6972, -3.9796, -4.4391, -3.8891, -4.8959, -3.9691, -4.2568, -4.9225, -4.5081, -4.7723, -4.9499, -4.6623, -4.9225, -4.8699, -4.9499, -4.9499, -5.0071, -5.037, -5.037, -5.096, -5.994, -6.4459, -5.2564, -5.907, -6.0893, -4.5852, -6.7824, -5.3008, -4.0878, -6.6001, -6.1946, -6.4459, -6.1946, -6.0893, -5.907, -5.8269, -6.1946, -5.994, -5.2138, -5.907, -6.3124, -6.4459, -5.7528, -5.5015, -4.6077, -5.6193, -3.4792, -6.1946, -5.4474, -3.0688, -3.892, -3.7571, -4.7809, -4.7809, -5.2564, -5.3008, -5.3473, -5.3961, -5.5586, -5.6193, -5.6838, -5.6838, -5.7528, -5.907, -4.8655, -4.5632, -4.9261, -5.3473, -4.233, -3.4502, -3.6297, -4.9261, -4.4029, -4.2175, -4.4406, -4.9261, -3.9259, -4.4798, -3.7967, -4.46, -4.0098, -4.2022, -4.1723, -4.4406, -4.3143, -4.8365, -4.5417, -4.2487, -4.7283, -4.5417, -5.4746, -5.8801, -6.4191, -5.8801, -4.7014, -4.8685, -5.8, -4.8386, -5.9671, -6.0624, -6.2855, -6.4191, -5.9671, -5.5318, -4.6761, -5.5924, -5.9671, -6.2855, -6.4191, -5.9671, -6.2855, -6.2855, -6.2855, -6.1677, -5.3205, -6.1677, -6.5732, -6.1677, -4.7274, -6.4191, -4.1906, -4.3045, -5.1869, -5.4205, -5.5318, -5.5924, -5.6569, -5.6569, -5.7259, -5.7259, -5.8, -5.8, -5.8801, -5.8801, -5.9671, -4.453, -3.5367, -5.2739, -5.3205, -4.4331, -5.4746, -3.7598, -4.1309, -4.0609, -4.5148, -4.7014, -4.0475, -4.6038, -4.4938, -4.2874, -4.453, -4.5583, -3.9583, -3.5287, -4.5363, -4.9638, -4.0883, -4.8096, -4.3396, -4.1023, -4.3576, -4.8096, -4.3947, -4.6761, -4.7541, -6.51, -6.3276, -5.6345, -5.9222, -5.8168, -6.51, -6.3276, -6.1735, -5.229, -6.1735, -4.9839, -4.5641, -5.7215, -5.9222, -5.229, -5.3468, -5.4803, -6.3276, -5.4803, -5.7215, -3.5655, -6.04, -4.7872, -5.0749, -4.9839, -5.4803, -6.1735, -6.1735, -6.1735, -6.1735, -4.3817, -4.9005, -3.7887, -5.3468, -5.6345, -5.7215, -5.9222, -6.04, -6.1735, -4.3352, -4.7182, -4.5641, -4.8236, -3.9297, -4.9413, -3.038, -3.8853, -3.5243, -4.1876, -4.1121, -5.1237, -3.3236, -4.1682, -4.6229, -4.094, -4.0419, -4.7521, -4.0085, -4.8613, -3.8853, -4.7521, -4.4305, -4.4818, -4.7872, -4.6229, -4.7182, -4.6854, -4.6854], "loglift": [30.0, 29.0, 28.0, 27.0, 26.0, 25.0, 24.0, 23.0, 22.0, 21.0, 20.0, 19.0, 18.0, 17.0, 16.0, 15.0, 14.0, 13.0, 12.0, 11.0, 10.0, 9.0, 8.0, 7.0, 6.0, 5.0, 4.0, 3.0, 2.0, 1.0, 1.9183, 1.9183, 1.9183, 1.9183, 1.9183, 1.9183, 1.9183, 1.9183, 1.9183, 1.9183, 1.9183, 1.9183, 1.9183, 1.9183, 1.9183, 1.9183, 1.9183, 1.9183, 1.9183, 1.9183, 1.9183, 1.9183, 1.9183, 1.9183, 1.9183, 1.9183, 1.9183, 1.9183, 1.9183, 1.9183, 1.9183, 1.9183, 1.9183, 1.9183, 1.9183, 1.9183, 1.9183, 1.9183, 1.9183, 1.9183, 1.9183, 1.9183, 1.9183, 1.9183, 1.9183, 1.9183, 1.9183, 1.9183, 1.9183, 1.9183, 1.9183, 1.9183, 1.9183, 1.9006, 1.9183, 1.8648, 1.8411, 1.8779, 1.7842, 1.6361, 1.7037, 1.5149, 1.5742, 1.3941, 1.7424, 1.5331, 1.6782, 1.5449, 1.5209, 1.5644, 1.3607, 1.2166, 1.198, 1.5177, 1.4306, 1.1283, 0.9901, 0.8448, 1.2182, 0.6976, 1.0349, 0.5719, 0.2973, 1.9706, 1.9706, 1.9706, 1.9706, 1.9706, 1.9706, 1.9706, 1.9706, 1.9706, 1.9706, 1.9706, 1.9706, 1.9706, 1.9706, 1.9706, 1.9706, 1.9706, 1.9706, 1.9706, 1.9706, 1.9706, 1.9706, 1.9706, 1.9706, 1.9706, 1.9706, 1.9706, 1.9706, 1.9706, 1.9706, 1.9706, 1.9706, 1.9706, 1.9706, 1.9706, 1.9706, 1.9706, 1.9706, 1.9706, 1.9706, 1.9706, 1.9706, 1.9706, 1.9706, 1.9706, 1.9706, 1.9706, 1.9706, 1.9706, 1.9706, 1.9706, 1.9706, 1.9027, 1.8188, 1.7808, 1.5521, 1.8903, 1.5248, 1.3244, 1.3249, 1.7469, 1.2449, 1.6206, 1.249, 1.4018, 1.3555, 1.3839, 1.4462, 1.5101, 1.48, 1.1301, 1.1626, 0.6142, 0.638, 0.858, 1.3062, 0.7452, 0.9496, 0.3994, 0.7395, 2.1083, 2.1083, 2.1083, 2.1083, 2.1083, 2.1083, 2.1083, 2.1083, 2.1083, 2.1083, 2.1083, 2.1083, 2.1083, 2.1083, 2.1083, 2.1083, 2.1083, 2.1083, 2.1083, 2.1083, 2.1083, 2.1083, 2.1083, 2.1083, 2.1083, 2.1083, 2.1083, 2.1083, 2.1083, 2.1083, 2.1083, 2.1083, 2.1083, 2.1083, 2.1083, 2.1083, 2.1083, 2.1083, 2.1083, 2.1083, 2.1083, 2.0959, 2.1083, 2.1083, 2.1083, 2.1083, 2.1083, 2.1083, 2.1083, 2.1083, 2.1083, 2.1083, 2.1083, 2.1083, 2.0873, 2.0821, 1.9967, 2.069, 1.8377, 1.7605, 1.9028, 2.0347, 2.0334, 1.885, 1.9991, 1.4699, 1.3096, 1.5181, 1.6576, 1.7439, 1.0223, 1.4583, 1.1374, 0.8912, 1.4256, 1.1273, 0.9508, 1.5846, 1.6943, 0.0433, 2.17, 2.17, 2.17, 2.17, 2.17, 2.17, 2.17, 2.17, 2.17, 2.17, 2.17, 2.17, 2.17, 2.17, 2.17, 2.17, 2.17, 2.17, 2.17, 2.17, 2.17, 2.17, 2.17, 2.17, 2.17, 2.17, 2.17, 2.17, 2.17, 2.17, 2.17, 2.17, 2.17, 2.17, 2.17, 2.17, 2.17, 2.17, 2.17, 2.17, 2.17, 2.17, 2.17, 2.17, 2.17, 2.17, 2.17, 2.17, 2.17, 2.17, 2.1375, 2.1075, 2.0477, 2.0958, 2.1266, 2.0395, 1.9126, 1.8569, 1.9436, 1.7915, 1.7889, 1.997, 1.6581, 1.6644, 1.8513, 1.8376, 1.5208, 1.3746, 1.7167, 1.6332, 1.2168, 1.538, 1.4855, 1.0589, 1.3192, 1.118, 1.4934, 1.3577, 1.2625, 1.0015, 0.4667, 1.3535, 1.5739, 1.1303, 2.1955, 2.1955, 2.1955, 2.1955, 2.1955, 2.1955, 2.1955, 2.1955, 2.1955, 2.1955, 2.1955, 2.1955, 2.1955, 2.1955, 2.1955, 2.1955, 2.1955, 2.1955, 2.1955, 2.1955, 2.1955, 2.1955, 2.1955, 2.1955, 2.1955, 2.1955, 2.1955, 2.1955, 2.1955, 2.1955, 2.1955, 2.1955, 2.1955, 2.1955, 2.1955, 2.1955, 2.1955, 2.1955, 2.1955, 2.1788, 2.1955, 2.1955, 2.1955, 2.1955, 2.1955, 2.1955, 2.1955, 2.1955, 2.1797, 2.1666, 2.1619, 2.0965, 1.8976, 1.7197, 1.9277, 2.03, 1.8676, 1.7787, 1.7659, 1.8941, 1.2755, 1.7069, 1.7255, 1.088, 1.0258, 1.4854, 1.568, 0.826, 1.4042, 0.9536, 0.5862, 0.73, 1.4603, 1.1004, 1.4612, 1.3393, 1.3345, 2.2342, 2.2342, 2.2342, 2.2342, 2.2342, 2.2342, 2.2342, 2.2342, 2.2342, 2.2342, 2.2342, 2.2342, 2.2342, 2.2342, 2.2342, 2.2342, 2.2342, 2.2342, 2.2342, 2.2342, 2.2342, 2.2342, 2.2342, 2.2342, 2.2342, 2.2342, 2.2342, 2.2342, 2.2342, 2.2342, 2.2342, 2.2277, 2.2342, 2.2342, 2.2342, 2.2342, 2.2342, 2.2342, 2.2342, 2.2342, 2.2342, 2.2035, 2.1957, 2.0863, 2.1436, 1.8569, 2.0286, 2.0727, 2.0697, 1.435, 1.4748, 1.5061, 1.1278, 1.8021, 1.033, 1.2573, 1.7296, 1.091, 1.3447, 1.5353, 0.7659, 1.2388, 1.0241, 1.1142, 0.8278, 0.8625, 0.8946, -0.0671, 2.3533, 2.3533, 2.3533, 2.3533, 2.3533, 2.3533, 2.3533, 2.3533, 2.3533, 2.3533, 2.3533, 2.3533, 2.3533, 2.3533, 2.3533, 2.3533, 2.3533, 2.3533, 2.3533, 2.3533, 2.3533, 2.3533, 2.3533, 2.3533, 2.3533, 2.3533, 2.3533, 2.3533, 2.3533, 2.3533, 2.3533, 2.3533, 2.3438, 2.3533, 2.3533, 2.3533, 2.3533, 2.3533, 2.3533, 2.3533, 2.3533, 2.3533, 2.3533, 2.3533, 2.3533, 2.3248, 2.3101, 2.3221, 2.3072, 2.1324, 2.0056, 1.9694, 2.2073, 2.0952, 2.0466, 2.0478, 2.1805, 1.8489, 1.976, 1.6282, 1.8736, 1.5915, 1.5921, 1.5312, 1.6653, 1.5553, 1.9998, 1.4035, 0.7485, 1.5522, 0.6796, 2.3746, 2.3746, 2.3746, 2.3746, 2.3746, 2.3746, 2.3746, 2.3746, 2.3746, 2.3746, 2.3746, 2.3746, 2.3746, 2.3746, 2.3746, 2.3746, 2.3746, 2.3746, 2.3746, 2.3746, 2.3746, 2.3746, 2.3746, 2.3746, 2.3746, 2.3746, 2.3746, 2.3746, 2.3746, 2.3746, 2.3746, 2.3746, 2.3746, 2.3746, 2.3746, 2.3746, 2.3746, 2.3746, 2.3746, 2.3746, 2.3746, 2.3746, 2.3746, 2.3746, 2.3746, 2.299, 2.23, 2.3308, 2.3288, 2.2144, 2.3218, 2.0808, 2.0663, 2.0388, 1.9733, 2.0279, 1.815, 1.984, 1.9339, 1.8262, 1.8908, 1.9288, 1.6564, 1.4411, 1.8952, 2.091, 1.5301, 1.9465, 1.4547, 1.2238, 1.4424, 1.7829, 0.8266, 1.2341, 1.574, 2.6361, 2.6361, 2.6361, 2.6361, 2.6361, 2.6361, 2.6361, 2.6361, 2.6361, 2.6361, 2.6361, 2.6361, 2.6361, 2.6361, 2.6361, 2.6361, 2.6361, 2.6361, 2.6361, 2.6361, 2.6361, 2.6361, 2.6361, 2.6361, 2.6361, 2.6361, 2.6361, 2.6361, 2.6361, 2.6361, 2.6361, 2.6361, 2.6227, 2.6361, 2.6361, 2.6361, 2.6361, 2.6361, 2.6361, 2.6138, 2.6037, 2.5811, 2.5297, 2.2994, 2.4097, 1.9318, 2.0902, 1.9038, 2.083, 2.0323, 2.4141, 1.6785, 1.9377, 2.1254, 1.7999, 1.7358, 2.1879, 1.6648, 2.2223, 1.0953, 1.8265, 0.947, 0.8822, 1.8705, 1.2023, 1.3815, 0.9256, 0.7067]}, "token.table": {"Topic": [1, 1, 4, 6, 8, 9, 4, 7, 1, 3, 3, 1, 1, 4, 9, 3, 9, 7, 8, 1, 8, 4, 4, 5, 4, 1, 3, 2, 5, 1, 2, 5, 6, 3, 6, 7, 9, 6, 1, 4, 6, 7, 2, 4, 7, 8, 9, 3, 8, 4, 5, 5, 9, 1, 8, 9, 1, 5, 9, 2, 9, 1, 8, 2, 1, 5, 2, 5, 9, 4, 1, 1, 8, 1, 3, 2, 1, 5, 9, 9, 6, 7, 5, 6, 9, 8, 3, 2, 3, 3, 3, 1, 2, 2, 7, 7, 1, 8, 6, 2, 8, 5, 3, 2, 2, 4, 6, 4, 3, 6, 3, 5, 3, 7, 5, 1, 1, 3, 6, 8, 2, 4, 9, 4, 1, 1, 2, 9, 1, 7, 9, 3, 4, 5, 2, 3, 8, 1, 7, 3, 4, 3, 8, 4, 4, 8, 9, 9, 6, 4, 6, 1, 3, 6, 1, 2, 3, 6, 9, 4, 9, 6, 7, 4, 5, 2, 6, 2, 9, 4, 8, 1, 7, 9, 7, 5, 5, 9, 7, 9, 3, 7, 4, 5, 7, 8, 9, 3, 7, 4, 1, 7, 6, 1, 3, 7, 1, 2, 6, 7, 6, 5, 9, 6, 4, 1, 8, 6, 1, 7, 9, 3, 6, 3, 5, 6, 8, 5, 2, 4, 9, 3, 6, 5, 7, 7, 8, 4, 5, 6, 5, 8, 7, 9, 1, 7, 1, 9, 9, 1, 3, 1, 2, 9, 1, 2, 6, 7, 4, 9, 1, 1, 5, 4, 1, 8, 8, 3, 9, 8, 9, 2, 3, 6, 3, 4, 2, 3, 8, 8, 1, 8, 1, 8, 4, 8, 5, 2, 4, 3, 2, 4, 6, 8, 6, 8, 5, 6, 4, 8, 9, 8, 9, 9, 2, 2, 4, 3, 4, 6, 7, 9, 9, 1, 4, 6, 1, 4, 9, 9, 6, 9, 9, 4, 4, 7, 8, 1, 2, 4, 1, 2, 5, 7, 2, 7, 9, 6, 4, 2, 6, 7, 3, 5, 5, 1, 2, 7, 5, 9, 6, 2, 1, 2, 7, 2, 5, 9, 7, 1, 4, 8, 9, 1, 4, 8, 4, 9, 7, 5, 2, 2, 4, 5, 5, 5, 5, 8, 5, 3, 7, 1, 2, 6, 9, 4, 7, 2, 6, 7, 1, 5, 1, 7, 9, 6, 2, 5, 1, 4, 6, 8, 9, 9, 8, 8, 3, 4, 2, 8, 2, 1, 3, 4, 2, 5, 1, 9, 5, 2, 4, 7, 2, 3, 6, 7, 4, 3, 5, 3, 4, 1, 2, 4, 5, 4, 4, 3, 6, 6, 3, 6, 5, 1, 1, 1, 5, 6, 8, 9, 9, 3, 6, 7, 5, 1, 7, 2, 6, 9, 5, 8, 1, 3, 7, 5, 2, 6, 7, 8, 5, 3, 6, 2, 4, 8, 9, 5, 7, 2, 4, 5, 8, 9, 7, 5, 1, 3, 5, 6, 2, 4, 5, 8, 9, 5, 8, 7, 7, 3, 7, 3, 5, 7, 3, 1, 7, 5, 9, 2, 4, 2, 7, 2, 2, 2, 3, 5, 3, 4, 5, 6, 9, 3, 4, 1, 2, 3, 8, 3, 3, 5, 9, 5, 1, 2, 4, 8, 2, 7, 5, 2, 6, 7, 8, 4, 8, 8, 6, 6, 2, 8, 5, 3, 7, 1, 1, 5, 6, 5, 6, 3, 1, 6, 2, 2, 3, 9, 3, 2, 6, 6, 4, 5, 1, 7, 9, 4, 8, 4, 8, 4, 8, 9, 9, 5, 8, 5, 6, 3, 1, 9, 4, 6, 2, 4, 7, 8, 9, 5, 1, 2, 7, 6, 7, 1, 2, 9, 5, 7, 9, 3, 8, 7, 8, 3, 1, 1, 2, 3, 6, 1, 7, 8, 2, 9, 2, 4, 2, 7, 2, 1, 2, 4, 5, 3, 1, 4, 5, 7, 3, 2, 1, 1, 5, 3, 4, 3, 1, 7, 9, 1, 7, 8, 8, 1, 3, 5, 7, 8, 8, 2, 3, 6, 9, 4, 3, 6, 6, 8, 4, 9, 4, 6, 8, 9, 8, 6, 8, 9, 6, 7, 1, 3, 6, 4, 3, 5, 1, 4, 5, 6, 8, 5, 2, 3, 5, 7, 6, 2, 4, 1, 2, 4, 9, 1, 7, 3, 7, 4, 1, 1, 2, 7, 1, 2, 3, 7, 6, 1, 8, 9, 4, 9, 7, 1, 4, 9, 8, 8, 1, 1, 5, 9, 5, 5, 4, 9, 8, 2, 3, 4, 6, 8, 7, 8, 9, 1, 3, 8, 6, 7, 9, 6, 8, 4, 2, 1, 3, 4, 9, 4, 8, 4, 3, 4, 8, 3, 3, 2, 5, 4, 1, 1, 4, 7, 8, 2, 6, 5, 9, 1, 7, 8, 3, 8, 5, 8, 4, 5, 8, 6, 8, 4, 7, 1, 2, 3, 1, 1, 8, 8, 2, 3, 2, 5, 7, 2, 8, 9, 4, 4, 5, 1, 3, 4, 6, 3, 5, 6, 1, 3, 6, 3, 9, 7, 7, 7, 7, 2, 4, 6, 6, 6, 3, 5, 2, 8, 4, 2, 7, 5, 6, 9, 2, 1, 8, 9, 8, 2, 5, 7, 4, 5, 2, 3, 3, 5, 6, 1, 2, 4, 6, 4, 2, 5, 6, 4, 3, 1, 2, 5, 1, 3, 5, 9, 1, 4, 5, 4, 5, 7, 1, 2, 5, 9, 1, 2, 5, 7, 8, 8, 5, 2, 6, 8, 9, 2, 7, 1, 8, 8, 9, 3, 6, 4, 7, 2, 3, 4, 7, 8, 5, 2, 4, 8, 7, 4, 5, 1, 4, 7, 3, 6, 9, 6, 9, 9, 7, 4, 7, 2, 3, 5, 6, 8, 7, 4, 8, 1, 7, 9, 1, 2, 8, 9, 3, 3, 4, 2, 3, 4, 4, 3, 1, 2, 9, 3, 7, 8], "Freq": [0.9691698596754815, 1.033781183653847, 0.4455425526595762, 0.330031520488575, 0.14851418421985874, 0.08250788012214375, 1.052840311392985, 1.0171777769040389, 0.9691698596754815, 1.0087745556731833, 0.9996864966130645, 1.0050650396634624, 0.31585523456008674, 0.6856369725816517, 0.9991799999621722, 0.9996864966130644, 0.9742004999631179, 0.8653201242384161, 0.1442200207064027, 0.8743562579420959, 0.12490803684887085, 1.0027050584695094, 0.9651036187769029, 1.0584761174174817, 0.980586564532682, 0.018746211794547253, 0.9748030133164572, 0.38083602428068264, 0.6151966546072565, 1.033781183653847, 0.2573183005247937, 0.7416821603361701, 1.0114989978938584, 1.0496708214437178, 0.4834869958634637, 0.3882547087994481, 0.13186008978094466, 0.9970490122096606, 0.9729801583475701, 0.034749291369556075, 0.9710390379781042, 1.0171777769040389, 0.6166826192734963, 0.18974849823799886, 0.023718562279749857, 0.023718562279749857, 0.14231137367849914, 0.9944249887361536, 1.0030779355983703, 0.014508333413069133, 0.986566672088701, 0.6195684335696635, 0.37955543678141546, 1.0089306744313988, 1.0325802278218519, 0.9849059999627126, 1.0176283526592558, 0.6283871132370816, 0.3678363589680477, 0.9987655653621215, 1.0277279999610913, 1.0176283526592558, 0.9655295636775757, 0.9992084769210403, 0.014175356665989096, 0.9780996099532476, 0.20911781258587236, 0.32861370549208513, 0.46304658501157453, 0.999223443683157, 0.9973337701275896, 0.9982578262474151, 1.0115071619479366, 1.0251663404567317, 1.0121825778207276, 1.0057499399450733, 0.9963253436663888, 1.0080724927785538, 1.0071734399618697, 1.0277279999610913, 0.9769563285086578, 0.033688149258919234, 0.271414864256635, 0.29925228623167455, 0.4314800406131121, 0.9940003072219145, 0.9996864966130644, 0.9588149427476366, 0.9981244864621064, 0.981510378492827, 0.981510378492827, 0.29378885585898107, 0.7077640618420907, 1.0057499399450733, 1.0061214967202994, 1.0171777769040389, 0.9893608984187208, 1.0071472172843678, 1.0013840079149199, 1.0169249392777964, 0.9957023625424999, 0.9828706804590901, 1.0496708214437178, 1.0057499399450733, 0.3579499652134089, 0.5212253879423322, 0.1193166550711363, 1.023594747187624, 0.9746943341977379, 1.0114989978938584, 1.0796614163421097, 1.0206733989382857, 0.987364140645373, 0.010970712673837478, 0.9720699037507483, 0.9950143892668277, 1.033781183653847, 0.04924034953107807, 0.016413449843692692, 0.9191531912467907, 0.9905113044913602, 0.011674943463200884, 0.9923701943720751, 1.0089719650849438, 0.9691698596754815, 1.0109771869556006, 1.0057499399450733, 1.079114399959146, 0.9867911298513996, 0.9911703905627426, 1.0277279999610913, 0.3770514652390938, 0.60195935678522, 0.019844813959952304, 0.9806061914464466, 0.04026019443471887, 0.9662446664332529, 0.9822612807691722, 0.015591448901097971, 1.0035314446769608, 0.9997902181832609, 0.24438868645352102, 0.7553832126745196, 1.0123464532624855, 0.3506665767798298, 0.5732049812747217, 0.074179468164964, 1.016557043439775, 1.006175318957575, 0.9870377919309233, 0.9931081070230611, 0.6698055204307602, 0.25516400778314674, 0.0744228356034178, 0.2089249022729124, 0.008193133422467153, 0.5284571057491314, 0.08193133422467154, 0.17205580187181022, 0.7197595079483344, 0.27808890079822013, 0.8409287840458137, 0.15490793390317623, 0.9341263281935342, 0.054948607540796134, 1.0092788871027754, 0.9831770259528305, 1.0057499399450733, 0.9810130908719509, 0.547830484983302, 0.45115451704507226, 0.21896996580569686, 0.20386858885357984, 0.5814030126565055, 1.0103049540871198, 0.9950651057749595, 1.001772039698688, 1.0116697499616991, 0.9889228386567046, 1.0116697499616991, 1.0121825778207276, 1.0012843741399133, 0.2765644789246193, 0.2663213500755593, 0.4506976693586388, 0.7181327830160965, 0.2821235933277522, 0.9746943341977379, 1.0103049540871198, 1.0027050584695094, 1.0854702428365393, 1.0087012954298387, 1.0174489919991165, 0.06204911866825536, 0.8997122206897027, 0.03102455933412768, 0.4148504880329822, 0.06285613455045184, 0.5028490764036148, 0.02514245382018074, 0.9970490122096606, 0.9720699037507483, 1.016557043439775, 1.002536348545432, 0.9870377919309233, 0.6790511351359918, 0.3183052195949962, 1.0017815402721708, 0.3953811356450534, 0.605427363956488, 0.9991799999621722, 0.4010767984583325, 0.6090425458070975, 0.981510378492827, 0.769593013625706, 0.13581053181630104, 0.10563041363490082, 0.9828706804590901, 1.0092788871027754, 0.35654119436599635, 0.6338510122062158, 0.31478505790225186, 0.688258855413398, 0.008559549563641175, 0.9929077493823762, 0.9889228386567046, 1.021233192351282, 0.4046484792820436, 0.332389822267393, 0.2601311652527423, 1.0027668480797194, 1.0115071619479363, 0.9709424234084009, 1.0277279999610913, 0.9501508029360473, 0.04634881965541694, 1.0251663404567317, 1.0277279999610913, 1.0277279999610913, 1.0854702428365393, 1.0087745556731833, 0.4933245182160702, 0.3976048355771312, 0.10308273514962661, 0.340825253731466, 0.5235356990308085, 0.0035136624096027418, 0.13000550915530146, 1.023594747187624, 1.0116697499616991, 1.033781183653847, 1.0854702428365393, 1.0584761174174817, 1.0158985460809504, 0.32033631321632045, 0.6824556238086827, 1.021233192351282, 0.9689080216629636, 0.03460385791653441, 0.2091569789435466, 0.8067483473536797, 0.9878699410127164, 0.9944249887361536, 1.00138400791492, 0.9746943341977379, 1.0089719650849438, 1.0057499399450733, 1.0055670054166708, 0.9891945039637907, 1.0115071619479366, 0.703369795528818, 0.3028397730749077, 0.9997752236652337, 1.0325802278218519, 1.052840311392985, 0.9957023625424999, 0.9897439020007618, 0.4123526502909511, 0.5833281394359796, 0.9996864966130644, 0.96849994216933, 0.12078899108084747, 0.857601836674017, 0.012078899108084747, 0.9908338200122901, 0.005760661744257501, 1.0206733989382857, 1.006175318957575, 1.036888185462788, 0.9957023625424999, 0.9991799999621722, 1.0325802278218519, 0.9742004999631179, 0.9991799999621722, 0.9961713690884536, 1.0007832735749742, 0.9651036187769029, 0.12552002747870036, 0.18257458542356417, 0.29953642921053497, 0.00570545579448638, 0.3851182661278307, 1.0277279999610913, 0.19989626837392327, 0.7995850734956931, 0.9103490981044726, 0.7799385739469626, 0.013683132876262502, 0.19156386026767505, 1.0033870736462234, 0.029019852624629656, 0.9576551366127787, 1.002034799962064, 0.9870377919309233, 0.9943491829822636, 0.8424411340464087, 0.1638079982868017, 0.8084480592940965, 0.179655124287577, 0.011228445267973562, 1.0131055599807701, 0.07640132390477836, 0.1528026478095567, 0.7767467930319133, 1.0169249392777966, 0.9713956933769924, 0.04047482055737468, 1.0013840079149199, 1.0123464532624855, 0.07775065791927945, 0.6531055265219473, 0.27990236850940603, 0.9996864966130645, 1.028233942634125, 1.0080724927785536, 0.6119480490370266, 0.2447792196148106, 0.14121878054700612, 0.42597522047904524, 0.5781092277929899, 1.0013840079149199, 1.0057499399450733, 0.49632364693894465, 0.021768581006094065, 0.4832624983352882, 0.5640757008662088, 0.20369400309057542, 0.22719715729333412, 0.9790336102701375, 0.3251603767711904, 0.3094268101532296, 0.18355827720954299, 0.17831375500355603, 0.1036642774515338, 0.16020842878873404, 0.7350739673836033, 0.3430166235695433, 0.6631654722344504, 1.0171777769040389, 0.9979917678507683, 1.0169249392777964, 0.9961713690884536, 1.0123464532624855, 1.0161370727207824, 1.0080724927785538, 1.0080724927785538, 0.04664262581598681, 0.9328525163197363, 1.0080724927785538, 1.0035314446769608, 0.9889228386567046, 0.3701671779306337, 0.4298715614678327, 0.023881753414879595, 0.17314271225787706, 0.26197528756728683, 0.7355459997081515, 0.8280455539852021, 0.15704312230753834, 0.014276647482503483, 0.9691698596754815, 0.9950651057749595, 0.7060316047996622, 0.26656295283252557, 0.021613212391826394, 0.9970490122096606, 0.9093717850084626, 0.06995167576988175, 0.1432579522362247, 0.450841202625766, 0.10112326040204096, 0.1558983597864798, 0.1432579522362247, 1.0277279999610913, 0.9834097407827161, 0.9655295636775757, 0.9996864966130644, 0.9870377919309233, 0.9878699410127164, 0.9957023625424999, 1.0301317566710144, 1.0854702428365393, 1.0121825778207276, 1.036888185462788, 1.0301317566710144, 1.0080724927785538, 1.002348647664372, 0.9991799999621722, 1.0368745640007981, 1.0459799375428762, 0.6874763223019611, 0.3172967641393667, 0.485497671828059, 0.13803365179425206, 0.37602270661192805, 1.0680366657492408, 1.0027050584695094, 0.9944249887361536, 1.0027668480797194, 1.0496708214437178, 0.9748521401786896, 0.3936937734260609, 0.028120983816147208, 0.17676046970149673, 0.39771105682836766, 0.980586564532682, 1.0027050584695094, 0.981510378492827, 1.0013840079149199, 1.00138400791492, 0.981510378492827, 0.9753740336833636, 1.0080724927785538, 0.9950143892668277, 1.033781183653847, 0.005523903619925323, 0.005523903619925323, 0.09943026515865581, 0.39219715701469793, 0.4943893739833164, 1.006316999961902, 1.0282489679448663, 0.9970490122096606, 0.964199767690287, 1.014002330971369, 1.007936654062501, 1.026958332451193, 1.0032197514169097, 0.9978826652299027, 0.9810130908719509, 0.9650177913498044, 0.029242963374236496, 0.011150130535212851, 0.18955221909861844, 0.8028093985353252, 1.0584761174174817, 0.29884472517149885, 0.2513012461669422, 0.4482670877572483, 1.0115071619479366, 1.0080724927785538, 0.9746943341977379, 0.9931081070230611, 0.48372433792255765, 0.38552466029918125, 0.06546645174891758, 0.06546645174891758, 0.9056414490128154, 0.1006268276680906, 0.08270703183629295, 0.1299681928856032, 0.5316880618047405, 0.02363058052465513, 0.22449051498422373, 0.9988120670432716, 1.0049707312623122, 0.9961594000715076, 0.6370276485590638, 0.3609823341834695, 0.9931081070230611, 0.122269547987912, 0.122269547987912, 0.33131103325756794, 0.31553431738815996, 0.11043701108585599, 0.3812357926062548, 0.619508162985164, 0.9985708663509164, 1.0061214967202994, 1.0196802265453258, 0.9837179816111429, 0.9944249887361536, 0.37808312375210545, 0.6157353729677146, 0.981510378492827, 1.0089306744313988, 1.0012843741399133, 0.019987518122694035, 0.9793883880120077, 0.9927124407235632, 0.9943491829822636, 0.9932755220852895, 1.0012843741399133, 1.02547052700282, 0.9588149427476366, 0.446840956259329, 0.5569322063522072, 0.9936714571674315, 0.038187634299625316, 0.9546908574906328, 1.088718292200838, 0.048640778036538324, 0.9484951717124973, 0.06431448555412551, 0.9218409596091324, 0.29613071706263994, 0.5227986733328088, 0.06580682601391999, 0.11698991291363553, 0.981510378492827, 0.1005633997259432, 0.7207043647025929, 0.18436623283089587, 1.0080724927785538, 0.570669700901932, 0.17743511708715531, 0.24457272895797086, 0.004795543705058252, 1.0169249392777966, 0.9889228386567046, 0.9828706804590901, 0.2406769366092062, 0.016045129107280412, 0.032090258214560824, 0.7059856807203382, 0.4478116051474115, 0.5597645064342643, 0.9834097407827161, 1.0045231427359698, 0.9710390379781042, 1.0007832735749742, 1.021233192351282, 1.014002330971369, 0.3035910210332388, 0.6964735188409596, 1.0007881671542562, 0.9950143892668277, 0.9979917678507683, 1.0029269724879784, 0.730402289465973, 0.2566278314339905, 1.0170723487280744, 1.0854702428365393, 1.0013840079149199, 1.0023974401452564, 0.5437183500923348, 0.24648565204185846, 0.21023776203570282, 1.0282489679448663, 0.9998337638277494, 0.9103490981044726, 1.0013840079149199, 0.9870377919309233, 1.0206733989382857, 0.4141819178645506, 0.4371920244125812, 0.14956569256219884, 0.3277943646216342, 0.6681962048056389, 1.0027050584695094, 0.9957023625424999, 1.036888185462788, 0.28218416326359463, 0.7103256523531865, 1.0277279999610913, 0.25731866481688714, 0.7455643365207242, 0.9592018101490196, 0.0259243732472708, 0.9944249887361536, 0.21607592140223797, 0.7922783784748726, 1.0027050584695094, 0.9931081070230611, 0.9806061914464466, 0.05039390049886074, 0.46614357961446184, 0.3968519664285283, 0.0818900883106487, 0.9828706804590901, 0.6676164727444776, 0.16568583995118422, 0.16568583995118422, 0.3212917602814524, 0.678858396723714, 0.7536248826894433, 0.006496766230081407, 0.24038035051301207, 1.0206733989382857, 0.08983302469627384, 0.8983302469627384, 0.9746943341977379, 1.0115071619479366, 1.03836898058954, 1.0015251833760819, 1.0282489679448663, 1.0854702428365393, 0.9867911298513996, 0.1272915652009654, 0.5091662608038616, 0.3727824409456844, 0.13427556144032446, 0.68358467642347, 0.18310303832771518, 0.9324798101598477, 0.0708212514045454, 1.0014701529665835, 1.0027050584695094, 1.0459799375428762, 0.964199767690287, 0.9806061914464466, 0.29500495634976404, 0.18028080665818913, 0.5080640914912602, 0.016389164241653556, 0.9896896316469338, 0.2602966473636349, 0.32804508982814257, 0.3102165523374827, 0.09983980994769558, 1.0282489679448663, 0.998435394927291, 0.9987833831655658, 1.0176283526592558, 0.9720699037507483, 0.11387441216261282, 0.8799386394383718, 0.9996864966130644, 0.925515533930797, 0.06610825242362836, 0.9956114999623071, 1.0009020483749156, 0.9889228386567046, 1.0030779355983703, 0.9957023625425, 0.11329153044859726, 0.7043777762673655, 0.1674744363153177, 0.004925718715156403, 0.004925718715156403, 0.9782339000417544, 0.13630088295982243, 0.21064681911972558, 0.24781978719967715, 0.4089026488794673, 0.9826509573001192, 0.07795097257524918, 0.909428013377907, 0.381912052617149, 0.6110592841874384, 1.0089719650849438, 1.0277279999610913, 0.6018685113357426, 0.006335458014060448, 0.3927983968717478, 0.9891881999625505, 0.9891945039637907, 0.1348026349254914, 0.8639623420224677, 0.9810130908719509, 0.26483025897934565, 0.7314359533715261, 0.5934519271256108, 0.07816196113361702, 0.3300171692308274, 1.023594747187624, 0.9324046648737943, 0.06430376999129615, 0.9691698596754815, 0.3486950391291418, 0.1215149378783373, 0.10038190520384385, 0.4279439116584922, 0.9828706804590901, 0.014534630854134837, 0.6976622809984722, 0.2761579862285619, 0.014534630854134837, 1.0013840079149199, 0.9927124407235632, 1.023594747187624, 0.07597489364845961, 0.6571828300591755, 0.18233974475630305, 0.08357238301330557, 1.0854702428365393, 0.9982775141575112, 1.0025427437462446, 1.0012843741399133, 1.0027050584695094, 0.9867911298513996, 0.23892222645962463, 0.2908618409073691, 0.46745653002970033, 0.19870292072011927, 0.26399102324244417, 0.33779496522420277, 0.20154153387326385, 0.9931081070230611, 0.34675239052202017, 0.5808102541243838, 0.07801928786745453, 1.023594747187624, 1.079114399959146, 0.9889228386567046, 1.0050650396634624, 0.8332315315872068, 0.16664630631744135, 0.9923498293352861, 0.9985391214101426, 1.0251663404567317, 0.027460772491173752, 0.8512839472263863, 0.10984308996469501, 1.0206733989382857, 1.0206733989382857, 0.7344942520213353, 0.2696244722609965, 1.0325802278218519, 0.008636575883534493, 0.15545836590362086, 0.5354677047791385, 0.25909727650603476, 0.05181945530120695, 1.0087012954298387, 0.8575968179763506, 0.1478615203407501, 0.4526490355449524, 0.05789696966272647, 0.48949256169396016, 0.9683042308048382, 0.0038887720112644104, 0.02722140407885087, 1.0153893786549886, 1.0325802278218519, 1.023594747187624, 0.9961713690884536, 0.10911864192415038, 0.9002287958742407, 0.8800453248561283, 0.1257207606937326, 0.9625435972112095, 0.028310105800329693, 1.023594747187624, 0.3272957374008002, 0.6303473461052448, 0.036366193044533354, 0.9996864966130644, 1.0046849290961297, 1.0005025489540553, 1.0161370727207824, 0.989849865412208, 1.0050650396634624, 0.23008863581563138, 0.427307466514744, 0.23666259683893512, 0.10518337637286006, 0.9806061914464466, 0.9973251265857918, 0.4559144804947617, 0.5453094766702051, 0.6745658417511493, 0.24983920064857384, 0.07495176019457216, 1.0121825778207276, 0.9891945039637907, 0.9720699037507483, 0.9834097407827161, 0.2749562138494746, 0.4811733742365806, 0.2405866871182903, 0.3652209920762728, 0.6422851929617212, 0.7236360081505624, 0.28316191623282877, 0.8309405291131007, 0.01806392454593697, 0.14451139636749577, 0.9950143892668277, 0.9950143892668277, 0.9957023625424999, 0.9957023625424999, 0.5953504345788904, 0.4068227969622418, 0.6337025234662592, 0.37065619297083086, 1.0113983577170842, 1.0169249392777966, 0.6592676368915676, 0.346115509368073, 0.9943491829822635, 0.5219714786526427, 0.4784738554315892, 1.0034946255389883, 0.3766483121244864, 0.15245288824086353, 0.46632648167793556, 0.5218800947467672, 0.0695840126329023, 0.408806074218301, 0.22880278891448785, 0.7650593254328187, 0.007150087153577745, 0.39248477817568134, 0.6050806996875088, 1.0113983577170842, 0.9790336102701375, 1.017177776904039, 0.9947400318252735, 0.9878699410127164, 0.1597666082321758, 0.8520885772382709, 1.0114989978938584, 1.0013840079149199, 1.0282489679448663, 1.0206733989382857, 0.9878699410127164, 1.0115071619479366, 1.052840311392985, 0.9878699410127164, 0.964199767690287, 0.28827241079020205, 0.23149148139213196, 0.4804540179836701, 1.02547052700282, 0.6849842572816875, 0.31135648058258525, 1.0491389999602807, 0.9655295636775757, 1.0057499399450733, 0.025443253789721974, 0.966843644009435, 0.512463239102493, 0.493483119135734, 0.022474853420008437, 0.9664186970603629, 0.2956414485638234, 0.25340695591184864, 0.44833538353634755, 0.03982533233334847, 0.7965066466669695, 0.09956333083337118, 0.05973799850002271, 1.0027050584695094, 0.6398322751064759, 0.22462196892035857, 0.13613452661839914, 0.9983830539071409, 0.9919966004852716, 0.23746794355815723, 0.518911432219677, 0.25505816159950223, 0.1368036373706887, 0.44949766564654864, 0.20101758960590996, 0.2149771444396537, 0.4353746907769471, 0.14512489692564903, 0.42500862671082934, 0.775147109221179, 0.23012179805003755, 0.964199767690287, 0.9832157996707784, 1.0092788871027754, 0.6532285102419871, 0.35173842859183924, 0.15982620619428842, 0.20954991478806706, 0.23086007561397218, 0.18823975396216192, 0.21310160825905122, 0.9957023625424999, 0.9720699037507483, 0.027602866419649475, 0.24842579777684526, 0.27602866419649474, 0.4416458627143916, 0.291884015572364, 0.7050121606901715, 1.0131055599807701, 0.9655295636775757, 0.9626918925061606, 0.03850767570024643, 1.0025427437462446, 0.9103490981044726, 1.036888185462788, 1.0012843741399133, 1.0057499399450733, 0.6573678442924916, 0.3443355374865432, 0.9790336102701375, 1.0115071619479366, 1.001772039698688, 0.5563010554683002, 0.44504084437464014, 0.9735756433748889, 1.0087012954298387, 0.3380283620543334, 0.6630556332604233, 1.0854702428365393, 0.03706231705709901, 0.9636202434845743, 0.817158602421032, 0.1831562384736796, 1.0491389999602807, 0.9103490981044726, 1.0491389999602807, 1.0116697499616991, 1.0171777769040389, 0.026958831508851703, 0.9705179343186613, 0.4099737835758981, 0.5876290897921206, 0.09074999401565668, 0.8167499461409101, 0.10587499301826613, 0.9709424234084009, 0.9943491829822636, 0.9655295636775757, 1.033781183653847, 0.4989240662467373, 0.4989240662467373, 0.071207857374683, 0.011867976229113834, 0.6408707163721471, 0.2729634532696182, 1.0087745556731833, 0.8074767894681799, 0.19309227574239085, 0.8559020512539226, 0.12644007575342037, 0.00972615967334003, 1.023594747187624, 0.9996864966130644, 0.48582920927162065, 0.32803852591844473, 0.18270500177736163, 0.9311267277626232, 0.06421563639742228, 0.9834097407827161], "Term": ["absence", "absent", "academic", "academic", "academic", "academic", "accident", "accompany", "accord", "accountability", "acm", "actively", "activity", "activity", "actual", "ad", "adapt", "add", "add", "additional", "additional", "additionally", "administrative", "administrator", "affect", "age", "age", "agent", "agent", "ahead", "ai", "ai", "algorithmic", "american", "analysis", "analysis", "analysis", "analytic", "announcement", "announcement", "annual", "anonymous", "answer", "answer", "answer", "answer", "answer", "app", "applicable", "application", "application", "apply", "apply", "appointment", "approval", "approve", "approximately", "area", "area", "argument", "arise", "arrive", "articulate", "artificial", "artificial_intelligence", "artificial_intelligence", "aspect", "aspect", "aspect", "assessment", "assign", "assignment", "assistance", "assume", "attack", "attempt", "attendance", "autonomous", "autumn", "avaialable", "bachelor", "bachelor", "base", "base", "base", "basic", "behavior", "belief", "bias", "black", "blame", "book", "book", "brain", "break", "building", "call", "campus", "capability", "capitalism", "card", "career", "careful", "carefully", "case", "case", "case", "catalog", "censorship", "centre", "certification", "chain", "chapter", "chapter", "charge", "cheat", "cheating", "check", "check", "check", "child", "choose", "choose", "circumstance", "cite", "civil", "claim", "classical", "classmate", "click", "co_operation", "code", "code", "code", "cognition", "collect", "collect", "comment", "comment", "common", "community", "company", "company", "complaint", "complete", "complete", "complete", "completion", "complex", "component", "computational", "compute", "compute", "compute", "computer", "computer", "computer", "computer", "computer", "computer_science", "computer_science", "computing", "computing", "conduct", "conduct", "connection", "consideration", "consist", "construct", "contact", "contact", "content", "content", "content", "context", "control", "cookie", "coordinator", "core", "correct", "cost", "coursework", "create", "create", "create", "credit", "credit", "criminal", "critical", "critically", "critique", "cryptography", "cultural", "culture", "culture", "culture", "current", "current", "current", "current", "curriculum", "cybersecurity", "cycle", "data", "database", "date", "date", "datum", "day", "day", "decide", "decision", "decision", "decision_making", "degree", "degree", "degree", "delivery", "depth", "describe", "describe", "design", "design", "detail", "detail", "detect", "detection", "develop", "develop", "develop", "development", "device", "dilemma", "disabilitie", "disability", "disability", "disciplinary", "disclose", "discontinue", "discretion", "discrimination", "discuss", "discuss", "discuss", "discussion", "discussion", "discussion", "discussion", "dismiss", "disposition", "disrupt", "disruption", "dissertation", "diverse", "document", "document", "documentation", "draft", "draft", "early", "early", "easy", "economy", "edit", "edition", "educational", "educator", "election", "electronic", "eligible", "email", "email", "emergency", "emphasize", "empirical", "employee", "employment", "end", "end", "energy", "engagement", "engineer", "engineer", "engineer", "engineering", "engineering", "english", "enhance", "enrol", "enroll", "entire", "equal", "equipment", "equivalent", "essay", "essential", "establish", "ethical", "ethical", "ethical", "ethical", "ethical", "ethical_theorie", "evaluation", "evaluation", "exact", "exam", "exam", "exam", "examination", "examine", "examine", "examiner", "exceptional", "excuse", "exercise", "exercise", "expect", "expect", "expect", "expectation", "explain", "explain", "explain", "express", "extension", "extension", "facility", "fact", "faculty", "faculty", "faculty", "fairness", "feature", "fee", "feedback", "feedback", "feedback", "field", "field", "figure", "film", "final", "final", "final", "find", "find", "find", "finish", "follow", "follow", "follow", "follow", "form", "form", "form", "format", "format", "frame", "freedom", "freely", "friend", "fully", "fund", "fundamental", "funding", "gain", "gain", "game", "gender", "generate", "give", "give", "give", "give", "goal", "goal", "good", "good", "good", "govern", "governance", "grade", "grade", "grade", "grant", "great", "great", "group", "group", "group", "group", "group", "group_webs", "grow", "guarantee", "hack", "harassment", "hard", "health", "helpful", "hesitate", "hide", "highlight", "historical", "home", "homework", "honor", "honour", "hope", "hour", "hour", "human", "human", "human", "ideally", "identify", "identity", "implementation", "improvement", "inappropriate", "include", "include", "include", "include", "inclusion", "inclusive", "income", "industrial", "industry", "inequality", "influence", "info", "inform", "informal", "information", "information", "information", "information", "information", "information_inserte", "informed", "innovation", "inquiry", "institution", "instructor", "intellectual", "intelligence", "intelligent", "intended_learning", "international", "international", "internet", "internet", "internet", "intersection", "introduction", "introduction", "introduction", "introductory", "investigate", "invisible", "invite", "issue", "issue", "issue", "issue", "key", "key", "knowledge", "knowledge", "knowledge", "knowledge", "knowledge", "lab", "language", "late", "law", "law", "leader", "learn", "learn", "learn", "learn", "learn", "learning", "learning", "lecture", "lecturer", "legislation", "length", "lesson", "level", "level", "liability", "license", "link", "literature", "literature", "live", "local", "long", "loop", "lose", "love", "machine", "machine", "machine_learne", "mail", "mail", "mailing", "main", "main", "major", "major", "make", "make", "make", "make", "man", "management", "management", "management", "master", "material", "material", "material", "material", "matter", "measure", "medicine", "meet", "meet", "meet", "meet", "meeting", "meeting", "memory", "method", "methodology", "mind", "minimize", "minimum", "minute", "minute", "miss", "mistake", "mode", "model", "module", "module", "money", "monitor", "month", "moodle", "moral", "moral", "moral", "morality", "movie", "multi", "music", "necessarily", "neural", "note", "note", "note", "number", "number", "objective", "obtain", "occur", "offer", "offer", "offering", "online", "online", "option", "option", "optional", "oral", "oral", "org", "organize", "oxford_university", "page", "page", "page", "page", "panel", "paper", "paper", "paper", "part", "part", "participation", "participation", "participation", "partner", "pass", "pass", "patent", "path", "pattern", "payment", "pdf", "pedagogical", "penalty", "people", "people", "people", "personal", "personal", "personal", "philosophical", "philosophical", "philosophy", "piazza", "picture", "play", "podcast", "point", "point", "point", "point", "police", "policy", "policy", "policy", "policy", "poor", "position", "post", "poster", "postgraduate", "practice", "practice", "predict", "prepare", "prepare", "prerequisite", "presentation", "primarily", "print", "prior", "privacy", "privacy", "privacy", "privacy", "privacy", "pro", "problem", "problem", "problem", "problem", "procedure", "proceeding", "proceeding", "process", "process", "produce", "profession", "professional", "professional", "professional", "professionalism", "profile", "program", "program", "programme_directory", "programming", "programming", "project", "project", "project", "promote", "proposal", "proposal", "protocol", "provide", "provide", "provide", "provide", "psychology", "public", "public", "public", "public", "publication", "put", "quality", "question", "question", "question", "question", "quietly", "quiz", "race", "random", "rate", "reach", "read", "read", "read", "reading", "reading", "reading", "reading", "reasoning", "receive", "receive", "receive", "recognize", "recommended_prerequisite", "refer", "reflection", "regard", "regard", "register", "registration", "regularly", "regulation", "regulation", "regulation", "regulatory", "reinforcement", "relate", "relate", "remain", "report", "report", "report", "report", "report", "represent", "request", "request", "require", "require", "require", "research", "research", "research", "researcher", "reserve", "respectful", "respond", "responsibility", "responsibility", "retrieve", "retrieve", "return", "return", "reuse", "review", "review", "review", "rise", "risk", "robot", "robotic", "rubric", "safety", "schedule", "schedule", "schedule", "schedule", "scholar", "science", "search", "search", "section", "section", "section", "secure", "seek", "senior", "sensitive", "service", "service", "service", "session", "session", "set", "set", "share", "share", "share", "sharing", "sheet", "shop", "shopping", "short", "short", "show", "show", "single", "singularity", "site", "site", "situation", "skill", "skill", "slide", "social", "social", "social", "society", "society", "society", "software", "software", "software", "solution", "solution", "solve", "sort", "speak", "speaker", "spend", "standard", "standard", "statistic", "statistical", "status", "storage", "story", "strictly", "strive", "strong", "strongly", "study", "study", "study", "style", "submit", "submit", "substantial", "sufficient", "suggest", "summary", "summary", "support", "support", "surveillance", "surveillance", "system", "system", "system", "talk", "talk", "talk", "talk", "task", "teach", "teach", "teach", "team", "tech", "technical", "technical", "technical", "technology", "technology", "technology", "technology", "term", "term", "term", "test", "test", "testing", "textbook", "theme", "theory", "theory", "time", "time", "time", "time", "time", "timely", "title", "tool", "tool", "tool", "tool", "topic", "topic", "total", "touch", "transfer", "transfer", "transparency", "treatment", "trouble", "trust", "ture", "turn", "turn", "tutor", "unable", "undergraduate", "understand", "understand", "unique", "unit", "university", "university", "unsure", "update", "update", "user", "user", "utilitarianism", "utility", "valid", "vary", "verbal", "version", "version", "view", "view", "visit", "visit", "visit", "visual", "voice", "warfare", "wealth", "web", "web", "website", "website", "website", "website", "wire", "woman", "woman", "word", "word", "word", "working", "workplace", "write", "write", "write", "wrong", "wrong", "zoom"]}, "R": 30, "lambda.step": 0.01, "plot.opts": {"xlab": "PC1", "ylab": "PC2"}, "topic.order": [1, 8, 4, 9, 7, 3, 5, 6, 2]}